{"v":"4.7.0","fr":25,"ip":0,"op":60,"w":1000,"h":1000,"nm":"Points_Cod_01","ddd":0,"assets":[{"id":"image_0","w":1000,"h":1000,"u":"images/","p":"img_0.png"},{"id":"image_1","w":1000,"h":1000,"u":"images/","p":"img_1.png"},{"id":"image_2","w":1000,"h":1000,"u":"images/","p":"img_2.png"},{"id":"image_3","w":1000,"h":1000,"u":"images/","p":"img_3.png"},{"id":"image_4","w":1000,"h":1000,"u":"images/","p":"img_4.png"},{"id":"image_5","w":1000,"h":1000,"u":"images/","p":"img_5.png"},{"id":"image_6","w":1000,"h":1000,"u":"images/","p":"img_6.png"},{"id":"image_7","w":1000,"h":1000,"u":"images/","p":"img_7.png"},{"id":"image_8","w":1000,"h":1000,"u":"images/","p":"img_8.png"},{"id":"image_9","w":1000,"h":1000,"u":"images/","p":"img_9.png"},{"id":"image_10","w":1000,"h":1000,"u":"images/","p":"img_10.png"},{"id":"image_11","w":1000,"h":1000,"u":"images/","p":"img_11.png"},{"id":"image_12","w":1000,"h":1000,"u":"images/","p":"img_12.png"}],"layers":[{"ddd":0,"ind":1,"ty":1,"nm":"Medium Red Solid 2","hd":true,"ks":{"o":{"a":0,"k":75},"r":{"a":0,"k":0},"p":{"a":0,"k":[500,541,0]},"a":{"a":0,"k":[500,500,0]},"s":{"a":0,"k":[100,100,100]}},"ao":0,"hasMask":true,"masksProperties":[{"inv":false,"mode":"a","pt":{"a":0,"k":{"i":[[0,0],[0,0],[0,0],[0,0]],"o":[[0,0],[0,0],[0,0],[0,0]],"v":[[747,351],[219,351],[219,628],[747,628]],"c":true}},"o":{"a":0,"k":100},"x":{"a":0,"k":0},"nm":"Mask 1"}],"ef":[{"ty":5,"nm":"Wave Warp","mn":"ADBE Wave Warp","ix":1,"en":1,"ef":[{"ty":7,"nm":"Wave Type","mn":"ADBE Wave Warp-0001","ix":1,"v":{"a":0,"k":1}},{"ty":0,"nm":"Wave Height","mn":"ADBE Wave Warp-0002","ix":2,"v":{"a":0,"k":22}},{"ty":0,"nm":"Wave Width","mn":"ADBE Wave Warp-0003","ix":3,"v":{"a":0,"k":316.7}},{"ty":0,"nm":"Direction","mn":"ADBE Wave Warp-0004","ix":4,"v":{"a":0,"k":90}},{"ty":7,"nm":"Wave Speed","mn":"ADBE Wave Warp-0005","ix":5,"v":{"a":0,"k":0.851}},{"ty":7,"nm":"Pinning","mn":"ADBE Wave Warp-0006","ix":6,"v":{"a":0,"k":1}},{"ty":0,"nm":"Phase","mn":"ADBE Wave Warp-0007","ix":7,"v":{"a":0,"k":0}},{"ty":7,"nm":"Antialiasing (Best Quality)","mn":"ADBE Wave Warp-0008","ix":8,"v":{"a":0,"k":1}}]}],"sw":1000,"sh":1000,"sc":"#ff8181","ip":0,"op":153,"st":0,"bm":0,"sr":1},{"ddd":0,"ind":2,"ty":3,"nm":"Null 9","ks":{"o":{"a":0,"k":0},"r":{"a":1,"k":[{"i":{"x":[0.496],"y":[1]},"o":{"x":[0.194],"y":[0]},"n":["0p496_1_0p194_0"],"t":0,"s":[-19.5],"e":[-1.4]},{"i":{"x":[0.838],"y":[1]},"o":{"x":[0.569],"y":[0]},"n":["0p838_1_0p569_0"],"t":19,"s":[-1.4],"e":[-19.5]},{"i":{"x":[0.496],"y":[1]},"o":{"x":[0.225],"y":[0]},"n":["0p496_1_0p225_0"],"t":30,"s":[-19.5],"e":[-1.4]},{"i":{"x":[0.867],"y":[1]},"o":{"x":[0.569],"y":[0]},"n":["0p867_1_0p569_0"],"t":49,"s":[-1.4],"e":[-19.5]},{"t":60}]},"p":{"a":1,"k":[{"i":{"x":0.795,"y":1},"o":{"x":0.066,"y":0},"n":"0p795_1_0p066_0","t":0,"s":[297,528,0],"e":[301,484,0],"to":[0,0,0],"ti":[0,0,0]},{"i":{"x":0.801,"y":1},"o":{"x":0.123,"y":0},"n":"0p801_1_0p123_0","t":16,"s":[301,484,0],"e":[297,530,0],"to":[0,0,0],"ti":[0,0,0]},{"i":{"x":0.831,"y":1},"o":{"x":0.168,"y":0},"n":"0p831_1_0p168_0","t":30,"s":[297,530,0],"e":[301,484,0],"to":[0,0,0],"ti":[0,0,0]},{"i":{"x":0.824,"y":1},"o":{"x":0.146,"y":0},"n":"0p824_1_0p146_0","t":46,"s":[301,484,0],"e":[297,528,0],"to":[0,0,0],"ti":[0,0,0]},{"t":60}]},"a":{"a":0,"k":[0,0,0]},"s":{"a":0,"k":[100,100,100]}},"ao":0,"ip":0,"op":153,"st":0,"bm":0,"sr":1},{"ddd":0,"ind":3,"ty":4,"nm":"R_Mustasch Outlines","parent":2,"ks":{"o":{"a":0,"k":100},"r":{"a":1,"k":[{"i":{"x":[0.667],"y":[1]},"o":{"x":[0.333],"y":[0]},"n":["0p667_1_0p333_0"],"t":0,"s":[7],"e":[-26]},{"i":{"x":[0.667],"y":[1]},"o":{"x":[0.333],"y":[0]},"n":["0p667_1_0p333_0"],"t":15,"s":[-26],"e":[7]},{"i":{"x":[0.667],"y":[1]},"o":{"x":[0.333],"y":[0]},"n":["0p667_1_0p333_0"],"t":30,"s":[7],"e":[-26]},{"i":{"x":[0.667],"y":[1]},"o":{"x":[0.333],"y":[0]},"n":["0p667_1_0p333_0"],"t":45,"s":[-26],"e":[7]},{"i":{"x":[0.667],"y":[1]},"o":{"x":[0.333],"y":[0]},"n":["0p667_1_0p333_0"],"t":60,"s":[7],"e":[-26]},{"i":{"x":[0.667],"y":[1]},"o":{"x":[0.333],"y":[0]},"n":["0p667_1_0p333_0"],"t":75,"s":[-26],"e":[7]},{"t":90}]},"p":{"a":0,"k":[-44.5,-14,0]},"a":{"a":0,"k":[253.5,494,0]},"s":{"a":0,"k":[100,100,100]}},"ao":0,"shapes":[{"ty":"gr","it":[{"ind":0,"ty":"sh","ix":1,"ks":{"a":1,"k":[{"i":{"x":0.667,"y":1},"o":{"x":0.333,"y":0},"n":"0p667_1_0p333_0","t":-25,"s":[{"i":[[0,0],[5.313,16.493],[-12.106,-26.844]],"o":[[-45.908,-9.032],[-10.969,-34.053],[0,0]],"v":[[42.786,53.076],[-31.818,-5.509],[1.824,-26.232]],"c":false}],"e":[{"i":[[0,0],[12.385,12.118],[-15.31,-0.667]],"o":[[-35.695,-11.527],[-25.533,-24.982],[0,0]],"v":[[42.786,53.076],[-36.859,4.827],[-30.258,-36.873]],"c":false}]},{"i":{"x":0.667,"y":1},"o":{"x":0.333,"y":0},"n":"0p667_1_0p333_0","t":-10,"s":[{"i":[[0,0],[12.385,12.118],[-15.31,-0.667]],"o":[[-35.695,-11.527],[-25.533,-24.982],[0,0]],"v":[[42.786,53.076],[-36.859,4.827],[-30.258,-36.873]],"c":false}],"e":[{"i":[[0,0],[5.313,16.493],[-12.106,-26.844]],"o":[[-45.908,-9.032],[-10.969,-34.053],[0,0]],"v":[[42.786,53.076],[-31.818,-5.509],[1.824,-26.232]],"c":false}]},{"i":{"x":0.667,"y":1},"o":{"x":0.333,"y":0},"n":"0p667_1_0p333_0","t":5,"s":[{"i":[[0,0],[5.313,16.493],[-12.106,-26.844]],"o":[[-45.908,-9.032],[-10.969,-34.053],[0,0]],"v":[[42.786,53.076],[-31.818,-5.509],[1.824,-26.232]],"c":false}],"e":[{"i":[[0,0],[12.385,12.118],[-15.31,-0.667]],"o":[[-35.695,-11.527],[-25.533,-24.982],[0,0]],"v":[[42.786,53.076],[-36.859,4.827],[-30.258,-36.873]],"c":false}]},{"i":{"x":0.667,"y":1},"o":{"x":0.333,"y":0},"n":"0p667_1_0p333_0","t":20,"s":[{"i":[[0,0],[12.385,12.118],[-15.31,-0.667]],"o":[[-35.695,-11.527],[-25.533,-24.982],[0,0]],"v":[[42.786,53.076],[-36.859,4.827],[-30.258,-36.873]],"c":false}],"e":[{"i":[[0,0],[5.313,16.493],[-12.106,-26.844]],"o":[[-45.908,-9.032],[-10.969,-34.053],[0,0]],"v":[[42.786,53.076],[-31.818,-5.509],[1.824,-26.232]],"c":false}]},{"i":{"x":0.667,"y":1},"o":{"x":0.333,"y":0},"n":"0p667_1_0p333_0","t":35,"s":[{"i":[[0,0],[5.313,16.493],[-12.106,-26.844]],"o":[[-45.908,-9.032],[-10.969,-34.053],[0,0]],"v":[[42.786,53.076],[-31.818,-5.509],[1.824,-26.232]],"c":false}],"e":[{"i":[[0,0],[12.385,12.118],[-15.31,-0.667]],"o":[[-35.695,-11.527],[-25.533,-24.982],[0,0]],"v":[[42.786,53.076],[-36.859,4.827],[-30.258,-36.873]],"c":false}]},{"i":{"x":0.667,"y":1},"o":{"x":0.333,"y":0},"n":"0p667_1_0p333_0","t":50,"s":[{"i":[[0,0],[12.385,12.118],[-15.31,-0.667]],"o":[[-35.695,-11.527],[-25.533,-24.982],[0,0]],"v":[[42.786,53.076],[-36.859,4.827],[-30.258,-36.873]],"c":false}],"e":[{"i":[[0,0],[5.313,16.493],[-12.106,-26.844]],"o":[[-45.908,-9.032],[-10.969,-34.053],[0,0]],"v":[[42.786,53.076],[-31.818,-5.509],[1.824,-26.232]],"c":false}]},{"i":{"x":0.667,"y":1},"o":{"x":0.333,"y":0},"n":"0p667_1_0p333_0","t":65,"s":[{"i":[[0,0],[5.313,16.493],[-12.106,-26.844]],"o":[[-45.908,-9.032],[-10.969,-34.053],[0,0]],"v":[[42.786,53.076],[-31.818,-5.509],[1.824,-26.232]],"c":false}],"e":[{"i":[[0,0],[12.385,12.118],[-15.31,-0.667]],"o":[[-35.695,-11.527],[-25.533,-24.982],[0,0]],"v":[[42.786,53.076],[-36.859,4.827],[-30.258,-36.873]],"c":false}]},{"i":{"x":0.667,"y":1},"o":{"x":0.333,"y":0},"n":"0p667_1_0p333_0","t":80,"s":[{"i":[[0,0],[12.385,12.118],[-15.31,-0.667]],"o":[[-35.695,-11.527],[-25.533,-24.982],[0,0]],"v":[[42.786,53.076],[-36.859,4.827],[-30.258,-36.873]],"c":false}],"e":[{"i":[[0,0],[5.313,16.493],[-12.106,-26.844]],"o":[[-45.908,-9.032],[-10.969,-34.053],[0,0]],"v":[[42.786,53.076],[-31.818,-5.509],[1.824,-26.232]],"c":false}]},{"t":95}]},"nm":"Path 1","mn":"ADBE Vector Shape - Group"},{"ty":"st","c":{"a":0,"k":[0.314,0.314,0.314,1]},"o":{"a":0,"k":100},"w":{"a":0,"k":12.633},"lc":2,"lj":2,"nm":"Stroke 1","mn":"ADBE Vector Graphic - Stroke"},{"ty":"tr","p":{"a":0,"k":[210.293,440.955],"ix":2},"a":{"a":0,"k":[0,0],"ix":1},"s":{"a":0,"k":[100,100],"ix":3},"r":{"a":0,"k":0,"ix":6},"o":{"a":0,"k":100,"ix":7},"sk":{"a":0,"k":0,"ix":4},"sa":{"a":0,"k":0,"ix":5},"nm":"Transform"}],"nm":"Group 1","np":2,"cix":2,"ix":1,"mn":"ADBE Vector Group"}],"ip":0,"op":153,"st":0,"bm":0,"sr":1},{"ddd":0,"ind":4,"ty":4,"nm":"L_Mustasch Outlines","parent":2,"ks":{"o":{"a":0,"k":100},"r":{"a":1,"k":[{"i":{"x":[0.667],"y":[1]},"o":{"x":[0.333],"y":[0]},"n":["0p667_1_0p333_0"],"t":0,"s":[-12],"e":[17]},{"i":{"x":[0.667],"y":[1]},"o":{"x":[0.333],"y":[0]},"n":["0p667_1_0p333_0"],"t":15,"s":[17],"e":[-12]},{"i":{"x":[0.667],"y":[1]},"o":{"x":[0.333],"y":[0]},"n":["0p667_1_0p333_0"],"t":30,"s":[-12],"e":[17]},{"i":{"x":[0.667],"y":[1]},"o":{"x":[0.333],"y":[0]},"n":["0p667_1_0p333_0"],"t":45,"s":[17],"e":[-12]},{"t":60}]},"p":{"a":0,"k":[44.5,1.5,0]},"a":{"a":0,"k":[342.5,509.5,0]},"s":{"a":0,"k":[100,100,100]}},"ao":0,"shapes":[{"ty":"gr","it":[{"ind":0,"ty":"sh","ix":1,"ks":{"a":1,"k":[{"i":{"x":0.667,"y":1},"o":{"x":0.333,"y":0},"n":"0p667_1_0p333_0","t":-22,"s":[{"i":[[0,0],[-11.75,27.42],[12,-34.992]],"o":[[42.696,9.61],[10.158,-23.703],[0,0]],"v":[[-57.348,38.685],[47.19,5.165],[7.348,-13.303]],"c":false}],"e":[{"i":[[0,0],[-26.326,14.03],[26.837,4.243]],"o":[[42.696,9.61],[22.758,-12.128],[0,0]],"v":[[-57.348,38.685],[45.553,31.604],[38.656,-12.939]],"c":false}]},{"i":{"x":0.667,"y":1},"o":{"x":0.333,"y":0},"n":"0p667_1_0p333_0","t":-7,"s":[{"i":[[0,0],[-26.326,14.03],[26.837,4.243]],"o":[[42.696,9.61],[22.758,-12.128],[0,0]],"v":[[-57.348,38.685],[45.553,31.604],[38.656,-12.939]],"c":false}],"e":[{"i":[[0,0],[-11.75,27.42],[12,-34.992]],"o":[[42.696,9.61],[10.158,-23.703],[0,0]],"v":[[-57.348,38.685],[47.19,5.165],[7.348,-13.303]],"c":false}]},{"i":{"x":0.667,"y":1},"o":{"x":0.333,"y":0},"n":"0p667_1_0p333_0","t":8,"s":[{"i":[[0,0],[-11.75,27.42],[12,-34.992]],"o":[[42.696,9.61],[10.158,-23.703],[0,0]],"v":[[-57.348,38.685],[47.19,5.165],[7.348,-13.303]],"c":false}],"e":[{"i":[[0,0],[-26.326,14.03],[26.837,4.243]],"o":[[42.696,9.61],[22.758,-12.128],[0,0]],"v":[[-57.348,38.685],[45.553,31.604],[38.656,-12.939]],"c":false}]},{"i":{"x":0.667,"y":1},"o":{"x":0.333,"y":0},"n":"0p667_1_0p333_0","t":23,"s":[{"i":[[0,0],[-26.326,14.03],[26.837,4.243]],"o":[[42.696,9.61],[22.758,-12.128],[0,0]],"v":[[-57.348,38.685],[45.553,31.604],[38.656,-12.939]],"c":false}],"e":[{"i":[[0,0],[-11.75,27.42],[12,-34.992]],"o":[[42.696,9.61],[10.158,-23.703],[0,0]],"v":[[-57.348,38.685],[47.19,5.165],[7.348,-13.303]],"c":false}]},{"i":{"x":0.667,"y":1},"o":{"x":0.333,"y":0},"n":"0p667_1_0p333_0","t":38,"s":[{"i":[[0,0],[-11.75,27.42],[12,-34.992]],"o":[[42.696,9.61],[10.158,-23.703],[0,0]],"v":[[-57.348,38.685],[47.19,5.165],[7.348,-13.303]],"c":false}],"e":[{"i":[[0,0],[-26.326,14.03],[26.837,4.243]],"o":[[42.696,9.61],[22.758,-12.128],[0,0]],"v":[[-57.348,38.685],[45.553,31.604],[38.656,-12.939]],"c":false}]},{"i":{"x":0.667,"y":1},"o":{"x":0.333,"y":0},"n":"0p667_1_0p333_0","t":53,"s":[{"i":[[0,0],[-26.326,14.03],[26.837,4.243]],"o":[[42.696,9.61],[22.758,-12.128],[0,0]],"v":[[-57.348,38.685],[45.553,31.604],[38.656,-12.939]],"c":false}],"e":[{"i":[[0,0],[-11.75,27.42],[12,-34.992]],"o":[[42.696,9.61],[10.158,-23.703],[0,0]],"v":[[-57.348,38.685],[47.19,5.165],[7.348,-13.303]],"c":false}]},{"t":68}]},"nm":"Path 1","mn":"ADBE Vector Shape - Group"},{"ty":"st","c":{"a":0,"k":[0.314,0.314,0.314,1]},"o":{"a":0,"k":100},"w":{"a":0,"k":12.633},"lc":2,"lj":2,"nm":"Stroke 1","mn":"ADBE Vector Graphic - Stroke"},{"ty":"tr","p":{"a":0,"k":[399.652,470.65],"ix":2},"a":{"a":0,"k":[0,0],"ix":1},"s":{"a":0,"k":[100,100],"ix":3},"r":{"a":0,"k":0,"ix":6},"o":{"a":0,"k":100,"ix":7},"sk":{"a":0,"k":0,"ix":4},"sa":{"a":0,"k":0,"ix":5},"nm":"Transform"}],"nm":"Group 1","np":2,"cix":2,"ix":1,"mn":"ADBE Vector Group"}],"ip":0,"op":153,"st":0,"bm":0,"sr":1},{"ddd":0,"ind":5,"ty":4,"nm":"Beard Outlines","parent":2,"ks":{"o":{"a":0,"k":100},"r":{"a":1,"k":[{"i":{"x":[0.667],"y":[1]},"o":{"x":[0.333],"y":[0]},"n":["0p667_1_0p333_0"],"t":0,"s":[22],"e":[-12]},{"i":{"x":[0.667],"y":[1]},"o":{"x":[0.333],"y":[0]},"n":["0p667_1_0p333_0"],"t":15,"s":[-12],"e":[22]},{"i":{"x":[0.667],"y":[1]},"o":{"x":[0.333],"y":[0]},"n":["0p667_1_0p333_0"],"t":30,"s":[22],"e":[-12]},{"i":{"x":[0.667],"y":[1]},"o":{"x":[0.333],"y":[0]},"n":["0p667_1_0p333_0"],"t":45,"s":[-12],"e":[22]},{"t":60}]},"p":{"a":0,"k":[-21,96.5,0]},"a":{"a":0,"k":[277,604.5,0]},"s":{"a":0,"k":[100,100,100]}},"ao":0,"shapes":[{"ty":"gr","it":[{"ind":0,"ty":"sh","ix":1,"ks":{"a":1,"k":[{"i":{"x":0.667,"y":1},"o":{"x":0.333,"y":0},"n":"0p667_1_0p333_0","t":-24,"s":[{"i":[[0,0],[2.13,-12.327],[11.664,-7.896],[2.368,9.448]],"o":[[-12.166,2.531],[-2.281,13.203],[-10.834,7.334],[0,0]],"v":[[21.712,-35.649],[3.158,-13.135],[4.127,28.315],[-21.712,19.63]],"c":false}],"e":[{"i":[[0,0],[2.13,-12.327],[-0.041,-14.085],[9.161,3.309]],"o":[[-12.166,2.531],[-2.281,13.203],[0.038,13.083],[0,0]],"v":[[21.712,-35.649],[3.158,-13.135],[13.752,27.284],[-7.877,43.875]],"c":false}]},{"i":{"x":0.667,"y":1},"o":{"x":0.333,"y":0},"n":"0p667_1_0p333_0","t":-9,"s":[{"i":[[0,0],[2.13,-12.327],[-0.041,-14.085],[9.161,3.309]],"o":[[-12.166,2.531],[-2.281,13.203],[0.038,13.083],[0,0]],"v":[[21.712,-35.649],[3.158,-13.135],[13.752,27.284],[-7.877,43.875]],"c":false}],"e":[{"i":[[0,0],[2.13,-12.327],[11.664,-7.896],[2.368,9.448]],"o":[[-12.166,2.531],[-2.281,13.203],[-10.834,7.334],[0,0]],"v":[[21.712,-35.649],[3.158,-13.135],[4.127,28.315],[-21.712,19.63]],"c":false}]},{"i":{"x":0.667,"y":1},"o":{"x":0.333,"y":0},"n":"0p667_1_0p333_0","t":6,"s":[{"i":[[0,0],[2.13,-12.327],[11.664,-7.896],[2.368,9.448]],"o":[[-12.166,2.531],[-2.281,13.203],[-10.834,7.334],[0,0]],"v":[[21.712,-35.649],[3.158,-13.135],[4.127,28.315],[-21.712,19.63]],"c":false}],"e":[{"i":[[0,0],[2.13,-12.327],[-0.041,-14.085],[9.161,3.309]],"o":[[-12.166,2.531],[-2.281,13.203],[0.038,13.083],[0,0]],"v":[[21.712,-35.649],[3.158,-13.135],[13.752,27.284],[-7.877,43.875]],"c":false}]},{"i":{"x":0.667,"y":1},"o":{"x":0.333,"y":0},"n":"0p667_1_0p333_0","t":21,"s":[{"i":[[0,0],[2.13,-12.327],[-0.041,-14.085],[9.161,3.309]],"o":[[-12.166,2.531],[-2.281,13.203],[0.038,13.083],[0,0]],"v":[[21.712,-35.649],[3.158,-13.135],[13.752,27.284],[-7.877,43.875]],"c":false}],"e":[{"i":[[0,0],[2.13,-12.327],[11.664,-7.896],[2.368,9.448]],"o":[[-12.166,2.531],[-2.281,13.203],[-10.834,7.334],[0,0]],"v":[[21.712,-35.649],[3.158,-13.135],[4.127,28.315],[-21.712,19.63]],"c":false}]},{"i":{"x":0.667,"y":1},"o":{"x":0.333,"y":0},"n":"0p667_1_0p333_0","t":36,"s":[{"i":[[0,0],[2.13,-12.327],[11.664,-7.896],[2.368,9.448]],"o":[[-12.166,2.531],[-2.281,13.203],[-10.834,7.334],[0,0]],"v":[[21.712,-35.649],[3.158,-13.135],[4.127,28.315],[-21.712,19.63]],"c":false}],"e":[{"i":[[0,0],[2.13,-12.327],[-0.041,-14.085],[9.161,3.309]],"o":[[-12.166,2.531],[-2.281,13.203],[0.038,13.083],[0,0]],"v":[[21.712,-35.649],[3.158,-13.135],[13.752,27.284],[-7.877,43.875]],"c":false}]},{"i":{"x":0.667,"y":1},"o":{"x":0.333,"y":0},"n":"0p667_1_0p333_0","t":51,"s":[{"i":[[0,0],[2.13,-12.327],[-0.041,-14.085],[9.161,3.309]],"o":[[-12.166,2.531],[-2.281,13.203],[0.038,13.083],[0,0]],"v":[[21.712,-35.649],[3.158,-13.135],[13.752,27.284],[-7.877,43.875]],"c":false}],"e":[{"i":[[0,0],[2.13,-12.327],[11.664,-7.896],[2.368,9.448]],"o":[[-12.166,2.531],[-2.281,13.203],[-10.834,7.334],[0,0]],"v":[[21.712,-35.649],[3.158,-13.135],[4.127,28.315],[-21.712,19.63]],"c":false}]},{"t":66}]},"nm":"Path 1","mn":"ADBE Vector Shape - Group"},{"ty":"st","c":{"a":0,"k":[0.314,0.314,0.314,1]},"o":{"a":0,"k":100},"w":{"a":0,"k":12.633},"lc":2,"lj":2,"nm":"Stroke 1","mn":"ADBE Vector Graphic - Stroke"},{"ty":"tr","p":{"a":0,"k":[256.418,638.702],"ix":2},"a":{"a":0,"k":[0,0],"ix":1},"s":{"a":0,"k":[100,100],"ix":3},"r":{"a":0,"k":0,"ix":6},"o":{"a":0,"k":100,"ix":7},"sk":{"a":0,"k":0,"ix":4},"sa":{"a":0,"k":0,"ix":5},"nm":"Transform"}],"nm":"Group 1","np":2,"cix":2,"ix":1,"mn":"ADBE Vector Group"}],"ip":0,"op":153,"st":0,"bm":0,"sr":1},{"ddd":0,"ind":6,"ty":4,"nm":"Fin Outlines","ks":{"o":{"a":0,"k":100},"r":{"a":1,"k":[{"i":{"x":[0.287],"y":[1]},"o":{"x":[0.593],"y":[0]},"n":["0p287_1_0p593_0"],"t":0,"s":[-19],"e":[23]},{"i":{"x":[0.667],"y":[1]},"o":{"x":[0.472],"y":[-0.001]},"n":["0p667_1_0p472_-0p001"],"t":14,"s":[23],"e":[-19]},{"i":{"x":[0.287],"y":[1]},"o":{"x":[0.593],"y":[0]},"n":["0p287_1_0p593_0"],"t":30,"s":[-19],"e":[23]},{"i":{"x":[0.629],"y":[1]},"o":{"x":[0.472],"y":[-0.001]},"n":["0p629_1_0p472_-0p001"],"t":44,"s":[23],"e":[-19]},{"t":60}]},"p":{"a":1,"k":[{"i":{"x":0.667,"y":1},"o":{"x":0.333,"y":0},"n":"0p667_1_0p333_0","t":0,"s":[471,508,0],"e":[456,561.5,0],"to":[0,0,0],"ti":[0,0,0]},{"i":{"x":0.667,"y":1},"o":{"x":0.333,"y":0},"n":"0p667_1_0p333_0","t":16,"s":[456,561.5,0],"e":[471,508,0],"to":[0,0,0],"ti":[0,0,0]},{"i":{"x":0.667,"y":1},"o":{"x":0.333,"y":0},"n":"0p667_1_0p333_0","t":30,"s":[471,508,0],"e":[456,561.5,0],"to":[0,0,0],"ti":[0,0,0]},{"i":{"x":0.667,"y":1},"o":{"x":0.333,"y":0},"n":"0p667_1_0p333_0","t":46,"s":[456,561.5,0],"e":[471,508,0],"to":[0,0,0],"ti":[0,0,0]},{"t":60}]},"a":{"a":0,"k":[476,533,0]},"s":{"a":0,"k":[100,100,100]}},"ao":0,"shapes":[{"ty":"gr","it":[{"ind":0,"ty":"sh","ix":1,"ks":{"a":0,"k":{"i":[[7.314,3.565],[12.174,3.177],[-7.873,-2.055],[-10.343,-5.042]],"o":[[-11.307,-5.512],[-7.872,-2.053],[11.129,2.903],[7.279,3.549]],"v":[[19.555,0.349],[-15.638,-12.752],[-18.996,-0.57],[13.178,11.256]],"c":true}},"nm":"Path 1","mn":"ADBE Vector Shape - Group"},{"ty":"fl","c":{"a":0,"k":[0.314,0.314,0.314,1]},"o":{"a":0,"k":100},"r":1,"nm":"Fill 1","mn":"ADBE Vector Graphic - Fill"},{"ty":"tr","p":{"a":0,"k":[516.909,552.766],"ix":2},"a":{"a":0,"k":[0,0],"ix":1},"s":{"a":0,"k":[100,100],"ix":3},"r":{"a":0,"k":0,"ix":6},"o":{"a":0,"k":100,"ix":7},"sk":{"a":0,"k":0,"ix":4},"sa":{"a":0,"k":0,"ix":5},"nm":"Transform"}],"nm":"Group 1","np":2,"cix":2,"ix":1,"mn":"ADBE Vector Group"},{"ty":"gr","it":[{"ind":0,"ty":"sh","ix":1,"ks":{"a":0,"k":{"i":[[7.995,1.481],[16.681,1.032],[-8.089,-0.5],[-15.339,-2.844]],"o":[[-16.434,-3.046],[-8.119,-0.503],[15.57,0.964],[7.946,1.472]],"v":[[24.903,-3.507],[-24.778,-9.644],[-24.778,2.988],[21.544,8.675]],"c":true}},"nm":"Path 1","mn":"ADBE Vector Shape - Group"},{"ty":"fl","c":{"a":0,"k":[0.314,0.314,0.314,1]},"o":{"a":0,"k":100},"r":1,"nm":"Fill 1","mn":"ADBE Vector Graphic - Fill"},{"ty":"tr","p":{"a":0,"k":[522.776,528.605],"ix":2},"a":{"a":0,"k":[0,0],"ix":1},"s":{"a":0,"k":[100,100],"ix":3},"r":{"a":0,"k":0,"ix":6},"o":{"a":0,"k":100,"ix":7},"sk":{"a":0,"k":0,"ix":4},"sa":{"a":0,"k":0,"ix":5},"nm":"Transform"}],"nm":"Group 2","np":2,"cix":2,"ix":2,"mn":"ADBE Vector Group"},{"ty":"gr","it":[{"ind":0,"ty":"sh","ix":1,"ks":{"a":0,"k":{"i":[[12.359,-1.13],[-0.767,-13.689],[-11.003,-5.1],[-16.823,-1.108],[-2.494,13.382],[14.392,8.111],[5.14,0.381],[6.529,0.047],[0.799,0]],"o":[[-12.763,1.166],[0.762,13.585],[14.904,6.907],[15.457,1.017],[2.259,-12.118],[-4.572,-2.577],[-6.512,-0.482],[-0.798,-0.006],[-12.466,0]],"v":[[-32.724,-36.318],[-57.247,-9.97],[-27.79,18.667],[19.905,37.129],[46.558,10.784],[43.623,-35.264],[26.549,-37.367],[6.978,-38.138],[4.584,-38.146]],"c":true}},"nm":"Path 2","mn":"ADBE Vector Shape - Group"},{"ty":"gf","o":{"a":0,"k":100},"r":1,"g":{"p":3,"k":{"a":0,"k":[0,0.035,0.671,0.843,0.5,0.237,0.812,0.865,1,0.439,0.953,0.886]}},"s":{"a":0,"k":[-50,-12]},"e":{"a":0,"k":[49,4]},"t":1,"nm":"Gradient Fill 1","mn":"ADBE Vector Graphic - G-Fill"},{"ty":"tr","p":{"a":0,"k":[523.569,545.827],"ix":2},"a":{"a":0,"k":[0,0],"ix":1},"s":{"a":0,"k":[100,100],"ix":3},"r":{"a":0,"k":0,"ix":6},"o":{"a":0,"k":100,"ix":7},"sk":{"a":0,"k":0,"ix":4},"sa":{"a":0,"k":0,"ix":5},"nm":"Transform"}],"nm":"Group 3","np":3,"cix":2,"ix":3,"mn":"ADBE Vector Group"}],"ip":0,"op":153,"st":0,"bm":0,"sr":1},{"ddd":0,"ind":7,"ty":4,"nm":"Scales","ks":{"o":{"a":0,"k":100},"r":{"a":0,"k":0},"p":{"a":0,"k":[500,500,0]},"a":{"a":0,"k":[500,500,0]},"s":{"a":0,"k":[100,100,100]}},"ao":0,"shapes":[{"ty":"gr","it":[{"ind":0,"ty":"sh","ix":1,"ks":{"a":0,"k":{"i":[[12.229,7.604],[-2.214,1.765],[1.413,7.409],[15.506,-6.86],[-7.375,3.263],[2.622,-10.089],[5.873,-2.049],[-4.858,-2.92],[-3.488,-8.232],[6.05,6.492],[-5.54,-5.945],[-7.073,14.577]],"o":[[2.598,-0.839],[5.993,-4.78],[-3.32,-17.41],[-7.419,3.283],[8.396,-3.714],[-1.891,7.28],[-5.042,1.76],[7.219,4.339],[4.603,10.864],[-5.555,-5.961],[10.834,11.627],[6.989,-14.403]],"v":[[3.018,-0.533],[10.307,-4.264],[17.084,-24.303],[-19.919,-42.655],[-13.544,-31.747],[4.721,-17.903],[-15.184,-8.949],[-16.693,2.596],[8.586,20.744],[-11.732,28.955],[-20.664,37.888],[20.349,31.816]],"c":true}},"nm":"Path 1","mn":"ADBE Vector Shape - Group"},{"ty":"fl","c":{"a":0,"k":[0.314,0.314,0.314,1]},"o":{"a":0,"k":100},"r":1,"nm":"Fill 1","mn":"ADBE Vector Graphic - Fill"},{"ty":"tr","p":{"a":1,"k":[{"i":{"x":0.667,"y":1},"o":{"x":0.167,"y":0.167},"n":"0p667_1_0p167_0p167","t":0,"s":[693.59,548.54],"e":[698.424,487.676],"to":[0,0],"ti":[0,0]},{"i":{"x":0.473,"y":1},"o":{"x":0.367,"y":0},"n":"0p473_1_0p367_0","t":12,"s":[698.424,487.676],"e":[693.59,560.54],"to":[0,0],"ti":[0,0]},{"i":{"x":0.833,"y":0.833},"o":{"x":0.167,"y":0},"n":"0p833_0p833_0p167_0","t":27,"s":[693.59,560.54],"e":[693.59,548.54],"to":[0,0],"ti":[0,0]},{"i":{"x":0.667,"y":1},"o":{"x":0.167,"y":0.167},"n":"0p667_1_0p167_0p167","t":30,"s":[693.59,548.54],"e":[698.424,487.676],"to":[0,0],"ti":[0,0]},{"i":{"x":0.473,"y":1},"o":{"x":0.367,"y":0},"n":"0p473_1_0p367_0","t":42,"s":[698.424,487.676],"e":[693.59,560.54],"to":[0,0],"ti":[0,0]},{"i":{"x":0.833,"y":0.833},"o":{"x":0.167,"y":0},"n":"0p833_0p833_0p167_0","t":57,"s":[693.59,560.54],"e":[693.59,548.54],"to":[0,0],"ti":[0,0]},{"t":60}],"ix":2},"a":{"a":0,"k":[0,0],"ix":1},"s":{"a":0,"k":[100,100],"ix":3},"r":{"a":1,"k":[{"i":{"x":[0.667],"y":[1]},"o":{"x":[0.167],"y":[0.033]},"n":["0p667_1_0p167_0p033"],"t":0,"s":[27],"e":[-6.5]},{"i":{"x":[0.833],"y":[0.967]},"o":{"x":[0.818],"y":[0]},"n":["0p833_0p967_0p818_0"],"t":12,"s":[-6.5],"e":[27]},{"i":{"x":[0.667],"y":[1]},"o":{"x":[0.167],"y":[0.033]},"n":["0p667_1_0p167_0p033"],"t":30,"s":[27],"e":[-6.5]},{"i":{"x":[0.667],"y":[1]},"o":{"x":[0.818],"y":[0]},"n":["0p667_1_0p818_0"],"t":42,"s":[-6.5],"e":[27]},{"t":60}],"ix":6},"o":{"a":0,"k":100,"ix":7},"sk":{"a":0,"k":0,"ix":4},"sa":{"a":0,"k":0,"ix":5},"nm":"Transform"}],"nm":"Group 1","np":2,"cix":2,"ix":1,"mn":"ADBE Vector Group"},{"ty":"gr","it":[{"ind":0,"ty":"sh","ix":1,"ks":{"a":0,"k":{"i":[[11.447,6.457],[6.652,17.315],[19.607,-0.485],[-8.145,0.202],[-8.512,-12.209],[7.523,-2.567],[8.327,-1.831],[-5.666,-1.75],[-5.625,-10.827],[11.563,1.019],[-7.993,-0.814],[3.037,-10.141],[5.173,9.088],[-4.032,-7.083],[-7.962,17.681],[7.235,7.451],[1.845,13.883]],"o":[[15.834,-4.457],[-7.715,-20.085],[-8.115,0.2],[13.994,-0.345],[6.077,8.716],[-8.074,2.754],[-6.346,1.395],[11.011,3.401],[8.5,16.359],[-8.13,-0.718],[9.714,0.988],[-2.935,9.797],[-4.02,-7.064],[9.715,17.066],[5.032,-11.175],[11.195,-4.149],[-1.671,-12.571]],"v":[[2.658,-22.621],[27.888,-52.365],[-26.396,-80.836],[-26.396,-68.204],[14.097,-51.51],[5.378,-37.322],[-19.245,-30.526],[-19.245,-18.344],[11.679,2.483],[-12.886,22.638],[-12.886,35.271],[2.323,55.052],[-18.555,57.879],[-29.461,64.255],[13.166,61.919],[7.828,32.544],[25.904,5.814]],"c":true}},"nm":"Path 1","mn":"ADBE Vector Shape - Group"},{"ty":"fl","c":{"a":0,"k":[0.314,0.314,0.314,1]},"o":{"a":0,"k":100},"r":1,"nm":"Fill 1","mn":"ADBE Vector Graphic - Fill"},{"ty":"tr","p":{"a":1,"k":[{"i":{"x":0.667,"y":1},"o":{"x":0.167,"y":0.167},"n":"0p667_1_0p167_0p167","t":0,"s":[614.397,517.968],"e":[614.397,493.231],"to":[0,0],"ti":[0,0]},{"i":{"x":0.667,"y":0.591},"o":{"x":0.333,"y":0},"n":"0p667_0p591_0p333_0","t":7,"s":[614.397,493.231],"e":[614.397,533.016],"to":[0,0],"ti":[0,0]},{"i":{"x":0.667,"y":1},"o":{"x":0.333,"y":0.349},"n":"0p667_1_0p333_0p349","t":18,"s":[614.397,533.016],"e":[614.397,549.968],"to":[0,0],"ti":[0,0]},{"i":{"x":0.833,"y":0.833},"o":{"x":0.333,"y":0},"n":"0p833_0p833_0p333_0","t":22,"s":[614.397,549.968],"e":[614.397,517.968],"to":[0,0],"ti":[0,0]},{"i":{"x":0.667,"y":1},"o":{"x":0.167,"y":0.167},"n":"0p667_1_0p167_0p167","t":30,"s":[614.397,517.968],"e":[614.397,493.231],"to":[0,0],"ti":[0,0]},{"i":{"x":0.667,"y":0.591},"o":{"x":0.333,"y":0},"n":"0p667_0p591_0p333_0","t":37,"s":[614.397,493.231],"e":[614.397,533.016],"to":[0,0],"ti":[0,0]},{"i":{"x":0.667,"y":1},"o":{"x":0.333,"y":0.349},"n":"0p667_1_0p333_0p349","t":48,"s":[614.397,533.016],"e":[614.397,549.968],"to":[0,0],"ti":[0,0]},{"i":{"x":0.833,"y":0.833},"o":{"x":0.333,"y":0},"n":"0p833_0p833_0p333_0","t":52,"s":[614.397,549.968],"e":[614.397,517.968],"to":[0,0],"ti":[0,0]},{"t":60}],"ix":2},"a":{"a":0,"k":[0,0],"ix":1},"s":{"a":0,"k":[100,100],"ix":3},"r":{"a":1,"k":[{"i":{"x":[0.58],"y":[0.95]},"o":{"x":[0.167],"y":[0.033]},"n":["0p58_0p95_0p167_0p033"],"t":0,"s":[16],"e":[-9.498]},{"i":{"x":[0.702],"y":[1]},"o":{"x":[0.346],"y":[0.13]},"n":["0p702_1_0p346_0p13"],"t":10,"s":[-9.498],"e":[-16]},{"i":{"x":[0.833],"y":[0.967]},"o":{"x":[0.333],"y":[0]},"n":["0p833_0p967_0p333_0"],"t":18,"s":[-16],"e":[16]},{"i":{"x":[0.58],"y":[0.95]},"o":{"x":[0.167],"y":[0.033]},"n":["0p58_0p95_0p167_0p033"],"t":30,"s":[16],"e":[-9.498]},{"i":{"x":[0.702],"y":[1]},"o":{"x":[0.346],"y":[0.13]},"n":["0p702_1_0p346_0p13"],"t":40,"s":[-9.498],"e":[-16]},{"i":{"x":[0.667],"y":[1]},"o":{"x":[0.333],"y":[0]},"n":["0p667_1_0p333_0"],"t":48,"s":[-16],"e":[16]},{"t":60}],"ix":6},"o":{"a":0,"k":100,"ix":7},"sk":{"a":0,"k":0,"ix":4},"sa":{"a":0,"k":0,"ix":5},"nm":"Transform"}],"nm":"Group 2","np":2,"cix":2,"ix":2,"mn":"ADBE Vector Group"},{"ty":"gr","it":[{"ind":0,"ty":"sh","ix":1,"ks":{"a":0,"k":{"i":[[8.142,4.984],[1.805,0.71],[1.153,7.504],[13.095,-4.744],[-7.67,2.779],[-5.028,-0.017],[7.459,-5.565],[3.531,-0.854],[5.04,-1.056],[-6.499,-0.786],[0.215,-15.855],[7.849,3.63],[-7.379,-3.412],[-4.519,24.253]],"o":[[-1.705,-1.044],[6.176,-3.259],[-2.924,-19.041],[-7.585,2.748],[4.694,-1.701],[2.902,0.009],[-2.969,2.216],[-5.005,1.211],[-7.563,1.584],[9.598,1.161],[-0.21,15.455],[-7.33,-3.39],[16.219,7.501],[1.816,-9.752]],"v":[[18.625,-5.677],[13.348,-8.271],[22.53,-23.861],[-20.547,-36.225],[-17.188,-24.044],[-2.733,-26.886],[7.274,-19.504],[-5.47,-16.046],[-20.541,-12.667],[-18.862,-0.26],[18.486,14.785],[-18.851,20.959],[-25.227,31.866],[30.79,18.649]],"c":true}},"nm":"Path 1","mn":"ADBE Vector Shape - Group"},{"ty":"fl","c":{"a":0,"k":[0.314,0.314,0.314,1]},"o":{"a":0,"k":100},"r":1,"nm":"Fill 1","mn":"ADBE Vector Graphic - Fill"},{"ty":"tr","p":{"a":1,"k":[{"i":{"x":0.833,"y":0.833},"o":{"x":0.333,"y":0},"n":"0p833_0p833_0p333_0","t":0,"s":[524.96,427.095],"e":[524.116,482.689],"to":[0,0],"ti":[0,0]},{"i":{"x":0.667,"y":1},"o":{"x":0.167,"y":0.167},"n":"0p667_1_0p167_0p167","t":12,"s":[524.116,482.689],"e":[523.96,500.095],"to":[0,0],"ti":[0,0]},{"i":{"x":0.833,"y":0.833},"o":{"x":0.333,"y":0},"n":"0p833_0p833_0p333_0","t":16,"s":[523.96,500.095],"e":[524.46,462.596],"to":[0,0],"ti":[0,0]},{"i":{"x":0.667,"y":1},"o":{"x":0.167,"y":0.167},"n":"0p667_1_0p167_0p167","t":24,"s":[524.46,462.596],"e":[524.96,427.095],"to":[0,0],"ti":[0,0]},{"i":{"x":0.833,"y":0.833},"o":{"x":0.333,"y":0},"n":"0p833_0p833_0p333_0","t":30,"s":[524.96,427.095],"e":[524.116,482.689],"to":[0,0],"ti":[0,0]},{"i":{"x":0.667,"y":1},"o":{"x":0.167,"y":0.167},"n":"0p667_1_0p167_0p167","t":42,"s":[524.116,482.689],"e":[523.96,500.095],"to":[0,0],"ti":[0,0]},{"i":{"x":0.833,"y":0.833},"o":{"x":0.333,"y":0},"n":"0p833_0p833_0p333_0","t":46,"s":[523.96,500.095],"e":[524.46,462.596],"to":[0,0],"ti":[0,0]},{"i":{"x":0.667,"y":1},"o":{"x":0.167,"y":0.167},"n":"0p667_1_0p167_0p167","t":54,"s":[524.46,462.596],"e":[524.96,427.095],"to":[0,0],"ti":[0,0]},{"t":60}],"ix":2},"a":{"a":0,"k":[0,0],"ix":1},"s":{"a":0,"k":[100,100],"ix":3},"r":{"a":1,"k":[{"i":{"x":[0.833],"y":[0.833]},"o":{"x":[0.167],"y":[0.167]},"n":["0p833_0p833_0p167_0p167"],"t":0,"s":[-3],"e":[-9.373]},{"i":{"x":[0.833],"y":[0.833]},"o":{"x":[0.167],"y":[0.167]},"n":["0p833_0p833_0p167_0p167"],"t":7,"s":[-9.373],"e":[1]},{"i":{"x":[0.833],"y":[0.833]},"o":{"x":[0.167],"y":[0.167]},"n":["0p833_0p833_0p167_0p167"],"t":16,"s":[1],"e":[5]},{"i":{"x":[0.833],"y":[0.833]},"o":{"x":[0.167],"y":[0.167]},"n":["0p833_0p833_0p167_0p167"],"t":24,"s":[5],"e":[-3]},{"i":{"x":[0.833],"y":[0.833]},"o":{"x":[0.167],"y":[0.167]},"n":["0p833_0p833_0p167_0p167"],"t":30,"s":[-3],"e":[-9.373]},{"i":{"x":[0.833],"y":[0.833]},"o":{"x":[0.167],"y":[0.167]},"n":["0p833_0p833_0p167_0p167"],"t":37,"s":[-9.373],"e":[1]},{"i":{"x":[0.833],"y":[0.833]},"o":{"x":[0.167],"y":[0.167]},"n":["0p833_0p833_0p167_0p167"],"t":46,"s":[1],"e":[5]},{"i":{"x":[0.833],"y":[0.833]},"o":{"x":[0.167],"y":[0.167]},"n":["0p833_0p833_0p167_0p167"],"t":54,"s":[5],"e":[-3]},{"t":60}],"ix":6},"o":{"a":0,"k":100,"ix":7},"sk":{"a":0,"k":0,"ix":4},"sa":{"a":0,"k":0,"ix":5},"nm":"Transform"}],"nm":"Group 3","np":2,"cix":2,"ix":3,"mn":"ADBE Vector Group"}],"ip":0,"op":153,"st":0,"bm":0,"sr":1},{"ddd":0,"ind":8,"ty":4,"nm":"Eye_Mid Outlines 2","parent":12,"ks":{"o":{"a":0,"k":100},"r":{"a":0,"k":0},"p":{"a":0,"k":[500,500,0]},"a":{"a":0,"k":[500,500,0]},"s":{"a":0,"k":[100,100,100]}},"ao":0,"shapes":[{"ty":"gr","it":[{"ind":0,"ty":"sh","ix":1,"ks":{"a":0,"k":{"i":[[1.848,2.339],[1.945,4.393],[2.359,-1.38],[-1.207,-2.727],[-3.6,-4.558],[-1.928,1.928]],"o":[[-2.984,-3.778],[-1.202,-2.716],[-2.799,1.637],[2.355,5.32],[1.842,2.333],[2.304,-2.304]],"v":[[7.854,2.835],[0.547,-9.593],[-6.978,-11.566],[-8.951,-4.041],[0.076,10.613],[7.854,10.613]],"c":true}},"nm":"Path 1","mn":"ADBE Vector Shape - Group"},{"ty":"fl","c":{"a":0,"k":[0.314,0.314,0.314,1]},"o":{"a":0,"k":100},"r":1,"nm":"Fill 1","mn":"ADBE Vector Graphic - Fill"},{"ty":"tr","p":{"a":0,"k":[346.769,459.538],"ix":2},"a":{"a":0,"k":[0,0],"ix":1},"s":{"a":0,"k":[100,100],"ix":3},"r":{"a":0,"k":0,"ix":6},"o":{"a":0,"k":100,"ix":7},"sk":{"a":0,"k":0,"ix":4},"sa":{"a":0,"k":0,"ix":5},"nm":"Transform"}],"nm":"Group 1","np":2,"cix":2,"ix":1,"mn":"ADBE Vector Group"},{"ty":"gr","it":[{"ind":0,"ty":"sh","ix":1,"ks":{"a":0,"k":{"i":[[5.4,0.01],[-0.017,1.153],[2.941,0],[0.043,-2.983],[0.062,-0.975],[7.052,2.763],[-0.368,0.344],[5.171,-4.831],[1.76,-2.364],[1.587,-1.149],[-1.604,-2.742],[-2.419,1.753],[-1.825,2.785],[-0.713,0.862],[-11.084,-5.193],[-5.817,3.782],[0,6.876]],"o":[[0.081,-1.148],[0.043,-2.972],[-3.018,0],[-0.015,0.983],[-7.697,-0.729],[0.355,-0.352],[5.183,-4.843],[-2.153,2.013],[-1.161,1.56],[-2.402,1.741],[1.387,2.372],[2.73,-1.977],[0.621,-0.948],[0.158,10.683],[8.008,3.752],[5.816,-3.783],[-5.248,0.524]],"v":[[18.54,-2.77],[18.698,-6.22],[13.198,-11.72],[7.698,-6.22],[7.576,-3.285],[-14.73,-8.336],[-13.655,-9.385],[-21.434,-17.163],[-27.249,-10.589],[-30.996,-5.199],[-32.969,2.326],[-25.444,4.299],[-19.247,-2.903],[-17.229,-5.601],[-2.195,18.242],[22.703,17.063],[34.574,-3.596]],"c":true}},"nm":"Path 1","mn":"ADBE Vector Shape - Group"},{"ty":"fl","c":{"a":0,"k":[0.314,0.314,0.314,1]},"o":{"a":0,"k":100},"r":1,"nm":"Fill 1","mn":"ADBE Vector Graphic - Fill"},{"ty":"tr","p":{"a":0,"k":[299.48,460.72],"ix":2},"a":{"a":0,"k":[0,0],"ix":1},"s":{"a":0,"k":[100,100],"ix":3},"r":{"a":0,"k":0,"ix":6},"o":{"a":0,"k":100,"ix":7},"sk":{"a":0,"k":0,"ix":4},"sa":{"a":0,"k":0,"ix":5},"nm":"Transform"}],"nm":"Group 2","np":2,"cix":2,"ix":2,"mn":"ADBE Vector Group"},{"ty":"gr","it":[{"ind":0,"ty":"sh","ix":1,"ks":{"a":0,"k":{"i":[[1.681,1.145],[2.603,1.039],[0,-9.655],[-26.818,-2.799],[-10.02,13.703],[2.705,4.986],[6.299,-1.043],[5.35,0.095],[9.939,5.687]],"o":[[-2.324,-1.583],[-12.998,-5.189],[-0.309,26.963],[18.298,1.91],[3.177,-4.344],[-3.87,-7.134],[-5.279,0.874],[-11.449,-0.204],[-1.759,-1.006]],"v":[[-31.318,-18.847],[-38.585,-23.014],[-52.226,-7.557],[-5.709,24.536],[44.039,14.5],[49.829,-11.048],[23.199,-9.978],[7.186,-9.292],[-26.206,-15.533]],"c":true}},"nm":"Path 1","mn":"ADBE Vector Shape - Group"},{"ty":"fl","c":{"a":0,"k":[1,1,1,1]},"o":{"a":0,"k":100},"r":1,"nm":"Fill 1","mn":"ADBE Vector Graphic - Fill"},{"ty":"tr","p":{"a":0,"k":[309.98,467.797],"ix":2},"a":{"a":0,"k":[0,0],"ix":1},"s":{"a":0,"k":[100,100],"ix":3},"r":{"a":0,"k":0,"ix":6},"o":{"a":0,"k":100,"ix":7},"sk":{"a":0,"k":0,"ix":4},"sa":{"a":0,"k":0,"ix":5},"nm":"Transform"}],"nm":"Group 3","np":2,"cix":2,"ix":3,"mn":"ADBE Vector Group"}],"ip":40,"op":41,"st":40,"bm":0,"sr":1},{"ddd":0,"ind":9,"ty":4,"nm":"Eye_Closed Outlines","parent":12,"ks":{"o":{"a":0,"k":100},"r":{"a":0,"k":0},"p":{"a":0,"k":[500,500,0]},"a":{"a":0,"k":[500,500,0]},"s":{"a":0,"k":[100,100,100]}},"ao":0,"shapes":[{"ty":"gr","it":[{"ind":0,"ty":"sh","ix":1,"ks":{"a":0,"k":{"i":[[6.331,3.187],[29.951,-9.984],[-6.743,2.248],[-2.415,0.624],[0.543,-1.725],[-2.122,6.74],[-0.511,3.559],[-6.255,-0.167],[-0.07,-2.821],[0.177,7.092],[0.063,2.535],[-5.196,-1.489],[-0.74,-4.129],[-2.676,0.735],[0.527,2.934],[0.242,1.85],[-2.251,-1.133]],"o":[[-28.148,-14.169],[-6.683,2.227],[2.377,-0.792],[-0.399,1.773],[-2.131,6.769],[1.086,-3.452],[6.218,-0.912],[0.07,2.82],[0.176,7.065],[-0.063,-2.536],[5.341,0.691],[0.397,4.176],[0.525,2.926],[3.081,-0.847],[-0.33,-1.843],[2.312,0.962],[6.307,3.175]],"v":[[45.704,-1.293],[-45.352,-8.136],[-42.428,2.471],[-35.236,0.351],[-36.66,5.604],[-26.053,8.529],[-23.747,-1.97],[-4.999,-3.069],[-4.789,5.393],[6.211,5.393],[6.022,-2.213],[21.847,1.078],[23.547,13.543],[30.313,17.385],[34.154,10.619],[33.298,5.083],[40.152,8.205]],"c":true}},"nm":"Path 1","mn":"ADBE Vector Shape - Group"},{"ty":"fl","c":{"a":0,"k":[0.314,0.314,0.314,1]},"o":{"a":0,"k":100},"r":1,"nm":"Fill 1","mn":"ADBE Vector Graphic - Fill"},{"ty":"tr","p":{"a":0,"k":[303.707,471.606],"ix":2},"a":{"a":0,"k":[0,0],"ix":1},"s":{"a":0,"k":[100,100],"ix":3},"r":{"a":0,"k":0,"ix":6},"o":{"a":0,"k":100,"ix":7},"sk":{"a":0,"k":0,"ix":4},"sa":{"a":0,"k":0,"ix":5},"nm":"Transform"}],"nm":"Group 1","np":2,"cix":2,"ix":1,"mn":"ADBE Vector Group"}],"ip":36,"op":40,"st":36,"bm":0,"sr":1},{"ddd":0,"ind":10,"ty":4,"nm":"Eye_Mid Outlines","parent":12,"ks":{"o":{"a":0,"k":100},"r":{"a":0,"k":0},"p":{"a":0,"k":[500,500,0]},"a":{"a":0,"k":[500,500,0]},"s":{"a":0,"k":[100,100,100]}},"ao":0,"shapes":[{"ty":"gr","it":[{"ind":0,"ty":"sh","ix":1,"ks":{"a":0,"k":{"i":[[1.848,2.339],[1.945,4.393],[2.359,-1.38],[-1.207,-2.727],[-3.6,-4.558],[-1.928,1.928]],"o":[[-2.984,-3.778],[-1.202,-2.716],[-2.799,1.637],[2.355,5.32],[1.842,2.333],[2.304,-2.304]],"v":[[7.854,2.835],[0.547,-9.593],[-6.978,-11.566],[-8.951,-4.041],[0.076,10.613],[7.854,10.613]],"c":true}},"nm":"Path 1","mn":"ADBE Vector Shape - Group"},{"ty":"fl","c":{"a":0,"k":[0.314,0.314,0.314,1]},"o":{"a":0,"k":100},"r":1,"nm":"Fill 1","mn":"ADBE Vector Graphic - Fill"},{"ty":"tr","p":{"a":0,"k":[346.769,459.538],"ix":2},"a":{"a":0,"k":[0,0],"ix":1},"s":{"a":0,"k":[100,100],"ix":3},"r":{"a":0,"k":0,"ix":6},"o":{"a":0,"k":100,"ix":7},"sk":{"a":0,"k":0,"ix":4},"sa":{"a":0,"k":0,"ix":5},"nm":"Transform"}],"nm":"Group 1","np":2,"cix":2,"ix":1,"mn":"ADBE Vector Group"},{"ty":"gr","it":[{"ind":0,"ty":"sh","ix":1,"ks":{"a":0,"k":{"i":[[5.4,0.01],[-0.017,1.153],[2.941,0],[0.043,-2.983],[0.062,-0.975],[7.052,2.763],[-0.368,0.344],[5.171,-4.831],[1.76,-2.364],[1.587,-1.149],[-1.604,-2.742],[-2.419,1.753],[-1.825,2.785],[-0.713,0.862],[-11.084,-5.193],[-5.817,3.782],[0,6.876]],"o":[[0.081,-1.148],[0.043,-2.972],[-3.018,0],[-0.015,0.983],[-7.697,-0.729],[0.355,-0.352],[5.183,-4.843],[-2.153,2.013],[-1.161,1.56],[-2.402,1.741],[1.387,2.372],[2.73,-1.977],[0.621,-0.948],[0.158,10.683],[8.008,3.752],[5.816,-3.783],[-5.248,0.524]],"v":[[18.54,-2.77],[18.698,-6.22],[13.198,-11.72],[7.698,-6.22],[7.576,-3.285],[-14.73,-8.336],[-13.655,-9.385],[-21.434,-17.163],[-27.249,-10.589],[-30.996,-5.199],[-32.969,2.326],[-25.444,4.299],[-19.247,-2.903],[-17.229,-5.601],[-2.195,18.242],[22.703,17.063],[34.574,-3.596]],"c":true}},"nm":"Path 1","mn":"ADBE Vector Shape - Group"},{"ty":"fl","c":{"a":0,"k":[0.314,0.314,0.314,1]},"o":{"a":0,"k":100},"r":1,"nm":"Fill 1","mn":"ADBE Vector Graphic - Fill"},{"ty":"tr","p":{"a":0,"k":[299.48,460.72],"ix":2},"a":{"a":0,"k":[0,0],"ix":1},"s":{"a":0,"k":[100,100],"ix":3},"r":{"a":0,"k":0,"ix":6},"o":{"a":0,"k":100,"ix":7},"sk":{"a":0,"k":0,"ix":4},"sa":{"a":0,"k":0,"ix":5},"nm":"Transform"}],"nm":"Group 2","np":2,"cix":2,"ix":2,"mn":"ADBE Vector Group"},{"ty":"gr","it":[{"ind":0,"ty":"sh","ix":1,"ks":{"a":0,"k":{"i":[[1.681,1.145],[2.603,1.039],[0,-9.655],[-26.818,-2.799],[-10.02,13.703],[2.705,4.986],[6.299,-1.043],[5.35,0.095],[9.939,5.687]],"o":[[-2.324,-1.583],[-12.998,-5.189],[-0.309,26.963],[18.298,1.91],[3.177,-4.344],[-3.87,-7.134],[-5.279,0.874],[-11.449,-0.204],[-1.759,-1.006]],"v":[[-31.318,-18.847],[-38.585,-23.014],[-52.226,-7.557],[-5.709,24.536],[44.039,14.5],[49.829,-11.048],[23.199,-9.978],[7.186,-9.292],[-26.206,-15.533]],"c":true}},"nm":"Path 1","mn":"ADBE Vector Shape - Group"},{"ty":"fl","c":{"a":0,"k":[1,1,1,1]},"o":{"a":0,"k":100},"r":1,"nm":"Fill 1","mn":"ADBE Vector Graphic - Fill"},{"ty":"tr","p":{"a":0,"k":[309.98,467.797],"ix":2},"a":{"a":0,"k":[0,0],"ix":1},"s":{"a":0,"k":[100,100],"ix":3},"r":{"a":0,"k":0,"ix":6},"o":{"a":0,"k":100,"ix":7},"sk":{"a":0,"k":0,"ix":4},"sa":{"a":0,"k":0,"ix":5},"nm":"Transform"}],"nm":"Group 3","np":2,"cix":2,"ix":3,"mn":"ADBE Vector Group"}],"ip":35,"op":36,"st":34,"bm":0,"sr":1},{"ddd":0,"ind":11,"ty":4,"nm":"Pupil Outlines","parent":12,"ks":{"o":{"a":1,"k":[{"t":0,"s":[100],"h":1},{"t":35,"s":[0],"h":1},{"t":41,"s":[100],"h":1}]},"r":{"a":0,"k":0},"p":{"a":0,"k":[500,500,0]},"a":{"a":0,"k":[500,500,0]},"s":{"a":0,"k":[100,100,100]}},"ao":0,"shapes":[{"ty":"gr","it":[{"ind":0,"ty":"sh","ix":1,"ks":{"a":0,"k":{"i":[[-7.399,8.297],[-1.223,3.816],[13.478,2.333],[-25.478,-11.936]],"o":[[2.419,-2.713],[4.384,-13.679],[-28.602,-4.95],[11.035,5.17]],"v":[[23.013,16.716],[28.577,6.88],[6.895,-22.816],[-7.483,22.596]],"c":true}},"nm":"Path 1","mn":"ADBE Vector Shape - Group"},{"ty":"fl","c":{"a":0,"k":[0.314,0.314,0.314,1]},"o":{"a":0,"k":100},"r":1,"nm":"Fill 1","mn":"ADBE Vector Graphic - Fill"},{"ty":"tr","p":{"a":0,"k":[304.767,456.366],"ix":2},"a":{"a":0,"k":[0,0],"ix":1},"s":{"a":0,"k":[100,100],"ix":3},"r":{"a":0,"k":0,"ix":6},"o":{"a":0,"k":100,"ix":7},"sk":{"a":0,"k":0,"ix":4},"sa":{"a":0,"k":0,"ix":5},"nm":"Transform"}],"nm":"Group 1","np":2,"cix":2,"ix":1,"mn":"ADBE Vector Group"}],"ip":0,"op":153,"st":0,"bm":0,"sr":1},{"ddd":0,"ind":12,"ty":4,"nm":"Eye Outlines","parent":2,"ks":{"o":{"a":1,"k":[{"t":0,"s":[100],"h":1},{"t":35,"s":[0],"h":1},{"t":41,"s":[100],"h":1}]},"r":{"a":0,"k":0},"p":{"a":0,"k":[202,-8,0]},"a":{"a":0,"k":[500,500,0]},"s":{"a":0,"k":[100,100,100]}},"ao":0,"shapes":[{"ty":"gr","it":[{"ind":0,"ty":"sh","ix":1,"ks":{"a":0,"k":{"i":[[63.452,0],[-0.003,-31.469],[-26.818,-2.8],[-8.397,16.906]],"o":[[-30.492,0],[-0.31,26.963],[18.299,1.91],[8.193,-16.497]],"v":[[-6.965,-50.792],[-56.177,2.057],[-9.29,48.882],[40.088,24.114]],"c":true}},"nm":"Path 1","mn":"ADBE Vector Shape - Group"},{"ty":"fl","c":{"a":0,"k":[1,1,1,1]},"o":{"a":0,"k":100},"r":1,"nm":"Fill 1","mn":"ADBE Vector Graphic - Fill"},{"ty":"tr","p":{"a":0,"k":[313.932,458.184],"ix":2},"a":{"a":0,"k":[0,0],"ix":1},"s":{"a":0,"k":[100,100],"ix":3},"r":{"a":0,"k":0,"ix":6},"o":{"a":0,"k":100,"ix":7},"sk":{"a":0,"k":0,"ix":4},"sa":{"a":0,"k":0,"ix":5},"nm":"Transform"}],"nm":"Group 1","np":2,"cix":2,"ix":1,"mn":"ADBE Vector Group"},{"ty":"gr","it":[{"ind":0,"ty":"sh","ix":1,"ks":{"a":0,"k":{"i":[[3.754,-5.992],[5.437,-7.175],[-4.226,5.577],[-4.779,7.629]],"o":[[-4.778,7.629],[-4.276,5.642],[5.437,-7.175],[3.768,-6.017]],"v":[[3.165,-13.67],[-12.156,8.532],[-2.658,14.084],[12.664,-8.118]],"c":true}},"nm":"Path 1","mn":"ADBE Vector Shape - Group"},{"ty":"fl","c":{"a":0,"k":[0.314,0.314,0.314,1]},"o":{"a":0,"k":100},"r":1,"nm":"Fill 1","mn":"ADBE Vector Graphic - Fill"},{"ty":"tr","p":{"a":0,"k":[349.385,418.924],"ix":2},"a":{"a":0,"k":[0,0],"ix":1},"s":{"a":0,"k":[100,100],"ix":3},"r":{"a":0,"k":0,"ix":6},"o":{"a":0,"k":100,"ix":7},"sk":{"a":0,"k":0,"ix":4},"sa":{"a":0,"k":0,"ix":5},"nm":"Transform"}],"nm":"Group 2","np":2,"cix":2,"ix":2,"mn":"ADBE Vector Group"},{"ty":"gr","it":[{"ind":0,"ty":"sh","ix":1,"ks":{"a":0,"k":{"i":[[0.681,-7.055],[-1.513,-8.355],[1.264,6.982],[-0.721,7.473]],"o":[[-0.811,8.394],[1.255,6.935],[-1.347,-7.438],[0.679,-7.032]],"v":[[-5.373,-12.526],[-5.335,12.646],[5.585,11.32],[5.509,-10.901]],"c":true}},"nm":"Path 1","mn":"ADBE Vector Shape - Group"},{"ty":"fl","c":{"a":0,"k":[0.314,0.314,0.314,1]},"o":{"a":0,"k":100},"r":1,"nm":"Fill 1","mn":"ADBE Vector Graphic - Fill"},{"ty":"tr","p":{"a":0,"k":[314.132,405.604],"ix":2},"a":{"a":0,"k":[0,0],"ix":1},"s":{"a":0,"k":[100,100],"ix":3},"r":{"a":0,"k":0,"ix":6},"o":{"a":0,"k":100,"ix":7},"sk":{"a":0,"k":0,"ix":4},"sa":{"a":0,"k":0,"ix":5},"nm":"Transform"}],"nm":"Group 3","np":2,"cix":2,"ix":3,"mn":"ADBE Vector Group"},{"ty":"gr","it":[{"ind":0,"ty":"sh","ix":1,"ks":{"a":0,"k":{"i":[[1.714,6.881],[2.136,3.739],[1.27,4.694],[-1.854,-6.853],[-2.194,-4.17],[-1.073,-4.308]],"o":[[-1.048,-4.206],[-2.416,-4.229],[-1.848,-6.826],[1.227,4.532],[2.043,3.883],[1.71,6.866]],"v":[[10.573,10.938],[5.361,-0.721],[0.175,-13.902],[-10.433,-10.978],[-5.632,2.153],[-0.034,13.862]],"c":true}},"nm":"Path 1","mn":"ADBE Vector Shape - Group"},{"ty":"fl","c":{"a":0,"k":[0.314,0.314,0.314,1]},"o":{"a":0,"k":100},"r":1,"nm":"Fill 1","mn":"ADBE Vector Graphic - Fill"},{"ty":"tr","p":{"a":0,"k":[278.075,415.332],"ix":2},"a":{"a":0,"k":[0,0],"ix":1},"s":{"a":0,"k":[100,100],"ix":3},"r":{"a":0,"k":0,"ix":6},"o":{"a":0,"k":100,"ix":7},"sk":{"a":0,"k":0,"ix":4},"sa":{"a":0,"k":0,"ix":5},"nm":"Transform"}],"nm":"Group 4","np":2,"cix":2,"ix":4,"mn":"ADBE Vector Group"}],"ip":0,"op":153,"st":0,"bm":0,"sr":1},{"ddd":0,"ind":13,"ty":4,"nm":"Mouth Outlines 2","parent":2,"ks":{"o":{"a":0,"k":100},"r":{"a":0,"k":0},"p":{"a":0,"k":[202,-8,0]},"a":{"a":0,"k":[500,500,0]},"s":{"a":0,"k":[100,100,100]}},"ao":0,"shapes":[{"ty":"gr","it":[{"ind":0,"ty":"sh","ix":1,"ks":{"a":1,"k":[{"i":{"x":0.667,"y":1},"o":{"x":0.667,"y":0},"n":"0p667_1_0p667_0","t":0,"s":[{"i":[[0,0],[-91.951,18.9],[46.148,4.438],[16.975,11.801]],"o":[[30.578,38.293],[0.759,65.746],[-55.64,-5.351],[0,0]],"v":[[-121.029,-55.466],[120.27,-10.281],[22.035,46.979],[-75.845,18.822]],"c":false}],"e":[{"i":[[0,0],[-32.951,-20.6],[65.284,17.641],[16.164,-4.202]],"o":[[39.848,69.585],[1.549,31.9],[-25.938,-7.009],[0,0]],"v":[[-121.029,-55.466],[89.27,5.219],[4.535,42.479],[-76.845,21.322]],"c":false}]},{"i":{"x":0.667,"y":1},"o":{"x":0.333,"y":0},"n":"0p667_1_0p333_0","t":15,"s":[{"i":[[0,0],[-32.951,-20.6],[65.284,17.641],[16.164,-4.202]],"o":[[39.848,69.585],[1.549,31.9],[-25.938,-7.009],[0,0]],"v":[[-121.029,-55.466],[89.27,5.219],[4.535,42.479],[-76.845,21.322]],"c":false}],"e":[{"i":[[0,0],[-91.951,18.9],[46.148,4.438],[16.975,11.801]],"o":[[30.578,38.293],[0.759,65.746],[-55.64,-5.351],[0,0]],"v":[[-121.029,-55.466],[120.27,-10.281],[22.035,46.979],[-75.845,18.822]],"c":false}]},{"i":{"x":0.667,"y":1},"o":{"x":0.667,"y":0},"n":"0p667_1_0p667_0","t":30,"s":[{"i":[[0,0],[-91.951,18.9],[46.148,4.438],[16.975,11.801]],"o":[[30.578,38.293],[0.759,65.746],[-55.64,-5.351],[0,0]],"v":[[-121.029,-55.466],[120.27,-10.281],[22.035,46.979],[-75.845,18.822]],"c":false}],"e":[{"i":[[0,0],[-32.951,-20.6],[65.284,17.641],[16.164,-4.202]],"o":[[39.848,69.585],[1.549,31.9],[-25.938,-7.009],[0,0]],"v":[[-121.029,-55.466],[89.27,5.219],[4.535,42.479],[-76.845,21.322]],"c":false}]},{"i":{"x":0.4,"y":1},"o":{"x":0.333,"y":0},"n":"0p4_1_0p333_0","t":45,"s":[{"i":[[0,0],[-32.951,-20.6],[65.284,17.641],[16.164,-4.202]],"o":[[39.848,69.585],[1.549,31.9],[-25.938,-7.009],[0,0]],"v":[[-121.029,-55.466],[89.27,5.219],[4.535,42.479],[-76.845,21.322]],"c":false}],"e":[{"i":[[0,0],[-91.951,18.9],[46.148,4.438],[16.975,11.801]],"o":[[30.578,38.293],[0.759,65.746],[-55.64,-5.351],[0,0]],"v":[[-121.029,-55.466],[120.27,-10.281],[22.035,46.979],[-75.845,18.822]],"c":false}]},{"t":60}]},"nm":"Path 1","mn":"ADBE Vector Shape - Group"},{"ty":"st","c":{"a":0,"k":[0.957,0.388,0.529,1]},"o":{"a":0,"k":100},"w":{"a":0,"k":17.37},"lc":2,"lj":2,"nm":"Stroke 1","mn":"ADBE Vector Graphic - Stroke"},{"ty":"tr","p":{"a":0,"k":[293.181,541.38],"ix":2},"a":{"a":0,"k":[0,0],"ix":1},"s":{"a":0,"k":[100,100],"ix":3},"r":{"a":0,"k":0,"ix":6},"o":{"a":0,"k":100,"ix":7},"sk":{"a":0,"k":0,"ix":4},"sa":{"a":0,"k":0,"ix":5},"nm":"Transform"}],"nm":"Group 1","np":2,"cix":2,"ix":1,"mn":"ADBE Vector Group"}],"ip":0,"op":153,"st":0,"bm":0,"sr":1},{"ddd":0,"ind":14,"ty":4,"nm":"Mouth Outlines","parent":2,"td":1,"ks":{"o":{"a":0,"k":100},"r":{"a":0,"k":0},"p":{"a":0,"k":[202,-8,0]},"a":{"a":0,"k":[500,500,0]},"s":{"a":0,"k":[100,100,100]}},"ao":0,"shapes":[{"ty":"gr","it":[{"ind":0,"ty":"sh","ix":1,"ks":{"a":0,"k":{"i":[[0,0],[-54.435,7.547],[45.836,6.954],[20.123,4.887]],"o":[[30.578,38.293],[-4.385,27.889],[-41.894,-6.346],[0,0]],"v":[[-121.029,-55.466],[78.805,-7.319],[-6.102,31.676],[-75.845,18.822]],"c":false},"x":"var $bm_rt;\n$bm_rt = thisComp.layer('Mouth Outlines 2').content('Group 1').content('Path 1').path;"},"nm":"Path 1","mn":"ADBE Vector Shape - Group"},{"ty":"st","c":{"a":0,"k":[0.957,0.388,0.529,1]},"o":{"a":0,"k":100},"w":{"a":0,"k":17.37},"lc":2,"lj":2,"nm":"Stroke 1","mn":"ADBE Vector Graphic - Stroke"},{"ty":"fl","c":{"a":0,"k":[1,0,0,1]},"o":{"a":0,"k":100},"r":1,"nm":"Fill 1","mn":"ADBE Vector Graphic - Fill"},{"ty":"tr","p":{"a":0,"k":[293.181,541.38],"ix":2},"a":{"a":0,"k":[0,0],"ix":1},"s":{"a":0,"k":[100,100],"ix":3},"r":{"a":0,"k":0,"ix":6},"o":{"a":0,"k":100,"ix":7},"sk":{"a":0,"k":0,"ix":4},"sa":{"a":0,"k":0,"ix":5},"nm":"Transform"}],"nm":"Group 1","np":3,"cix":2,"ix":1,"mn":"ADBE Vector Group"}],"ip":0,"op":153,"st":0,"bm":0,"sr":1},{"ddd":0,"ind":15,"ty":4,"nm":"Teeth Outlines","parent":2,"tt":1,"ks":{"o":{"a":0,"k":100},"r":{"a":0,"k":0},"p":{"a":0,"k":[202,-8,0]},"a":{"a":0,"k":[500,500,0]},"s":{"a":0,"k":[100,100,100]}},"ao":0,"shapes":[{"ty":"gr","it":[{"ind":0,"ty":"sh","ix":1,"ks":{"a":0,"k":{"i":[[0,-8.142],[0,0],[0,8.142],[0,0]],"o":[[0,0],[0,8.128],[0,0],[0,-8.128]],"v":[[-6.316,-22.897],[-6.316,22.897],[6.316,22.897],[6.316,-22.897]],"c":true}},"nm":"Path 1","mn":"ADBE Vector Shape - Group"},{"ty":"fl","c":{"a":0,"k":[0.698,0.698,0.698,1]},"o":{"a":0,"k":100},"r":1,"nm":"Fill 1","mn":"ADBE Vector Graphic - Fill"},{"ty":"tr","p":{"a":0,"k":[368.486,566.803],"ix":2},"a":{"a":0,"k":[0,0],"ix":1},"s":{"a":0,"k":[100,100],"ix":3},"r":{"a":0,"k":0,"ix":6},"o":{"a":0,"k":100,"ix":7},"sk":{"a":0,"k":0,"ix":4},"sa":{"a":0,"k":0,"ix":5},"nm":"Transform"}],"nm":"Group 1","np":2,"cix":2,"ix":1,"mn":"ADBE Vector Group"},{"ty":"gr","it":[{"ind":0,"ty":"sh","ix":1,"ks":{"a":0,"k":{"i":[[0.809,-8.024],[1.3,-12.897],[-0.809,8.026],[-1.3,12.897]],"o":[[-1.3,12.897],[-0.815,8.082],[1.301,-12.897],[0.814,-8.081]],"v":[[-4.366,-19.347],[-8.266,19.345],[4.366,19.345],[8.267,-19.347]],"c":true}},"nm":"Path 1","mn":"ADBE Vector Shape - Group"},{"ty":"fl","c":{"a":0,"k":[0.698,0.698,0.698,1]},"o":{"a":0,"k":100},"r":1,"nm":"Fill 1","mn":"ADBE Vector Graphic - Fill"},{"ty":"tr","p":{"a":0,"k":[304.271,561.684],"ix":2},"a":{"a":0,"k":[0,0],"ix":1},"s":{"a":0,"k":[100,100],"ix":3},"r":{"a":0,"k":0,"ix":6},"o":{"a":0,"k":100,"ix":7},"sk":{"a":0,"k":0,"ix":4},"sa":{"a":0,"k":0,"ix":5},"nm":"Transform"}],"nm":"Group 2","np":2,"cix":2,"ix":2,"mn":"ADBE Vector Group"},{"ty":"gr","it":[{"ind":0,"ty":"sh","ix":1,"ks":{"a":0,"k":{"i":[[0.154,-8.133],[0.241,-12.632],[-0.154,8.133],[0,0]],"o":[[-0.24,12.633],[-0.154,8.133],[0,0],[0.155,-8.133]],"v":[[-5.956,-18.949],[-6.676,18.949],[5.956,18.949],[6.675,-18.949]],"c":true}},"nm":"Path 1","mn":"ADBE Vector Shape - Group"},{"ty":"fl","c":{"a":0,"k":[0.698,0.698,0.698,1]},"o":{"a":0,"k":100},"r":1,"nm":"Fill 1","mn":"ADBE Vector Graphic - Fill"},{"ty":"tr","p":{"a":0,"k":[241.163,548.647],"ix":2},"a":{"a":0,"k":[0,0],"ix":1},"s":{"a":0,"k":[100,100],"ix":3},"r":{"a":0,"k":0,"ix":6},"o":{"a":0,"k":100,"ix":7},"sk":{"a":0,"k":0,"ix":4},"sa":{"a":0,"k":0,"ix":5},"nm":"Transform"}],"nm":"Group 3","np":2,"cix":2,"ix":3,"mn":"ADBE Vector Group"},{"ty":"gr","it":[{"ind":0,"ty":"sh","ix":1,"ks":{"a":0,"k":{"i":[[18.436,-0.705],[2.281,0.067],[23.857,0.308],[19.705,7.12],[0.616,19.168],[-10.627,2.535],[-5.925,-0.752],[-8.164,-0.813],[-19.59,-0.672],[-13.947,2.421],[-2.415,-0.134],[-3.045,-4.27],[0.961,-15.838]],"o":[[-2.105,0.08],[-23.849,-0.709],[-20.99,-0.271],[-20.926,-7.561],[-0.282,-8.786],[5.753,-1.372],[8.14,1.034],[19.506,1.94],[14.124,0.485],[2.382,-0.413],[5.237,0.292],[9.475,13.287],[-1.309,21.565]],"v":[[64.052,45.644],[57.47,45.657],[-14.111,43.528],[-75.348,26.645],[-92.897,-18.841],[-81.138,-44.352],[-61.383,-42.027],[-36.927,-39.257],[21.737,-35.336],[65.028,-37.144],[72.219,-37.953],[85.156,-29.95],[95.313,16.498]],"c":true}},"nm":"Path 1","mn":"ADBE Vector Shape - Group"},{"ty":"fl","c":{"a":0,"k":[1,1,1,1]},"o":{"a":0,"k":100},"r":1,"nm":"Fill 1","mn":"ADBE Vector Graphic - Fill"},{"ty":"tr","p":{"a":0,"k":[334.949,558.542],"ix":2},"a":{"a":0,"k":[0,0],"ix":1},"s":{"a":0,"k":[100,100],"ix":3},"r":{"a":0,"k":0,"ix":6},"o":{"a":0,"k":100,"ix":7},"sk":{"a":0,"k":0,"ix":4},"sa":{"a":0,"k":0,"ix":5},"nm":"Transform"}],"nm":"Group 4","np":2,"cix":2,"ix":4,"mn":"ADBE Vector Group"}],"ip":0,"op":153,"st":0,"bm":0,"sr":1},{"ddd":0,"ind":16,"ty":4,"nm":"Body 2","ks":{"o":{"a":0,"k":100},"r":{"a":0,"k":0},"p":{"a":0,"k":[500,500,0]},"a":{"a":0,"k":[500,500,0]},"s":{"a":0,"k":[100,100,100]}},"ao":0,"shapes":[{"ty":"gr","it":[{"ind":0,"ty":"sh","ix":1,"ks":{"a":1,"k":[{"i":{"x":0.833,"y":0.833},"o":{"x":0.167,"y":0.167},"n":"0p833_0p833_0p167_0p167","t":-16,"s":[{"i":[[0,-37.108],[-71.062,-18.104],[25.794,9.118],[-22.305,-16.618],[-99.131,6.303],[0.679,62.494],[175.394,2.27]],"o":[[0,3.325],[-3.562,26.896],[-26.206,-8.882],[70.468,42.675],[99.132,-6.304],[-4.321,-28.506],[-186,-2.407]],"v":[[-304.084,-28.266],[-226.674,18.16],[-241.03,52.938],[-247.044,80.73],[14.315,127.233],[303.084,-5.438],[-28.236,-133.537]],"c":true}],"e":[{"i":[[-13.199,-34.681],[-72.854,8.356],[27.35,-0.653],[-26.757,-7.597],[-99.131,6.303],[-24.595,74.506],[177,-3.407]],"o":[[1.183,3.108],[6.238,26.404],[-27.651,1.02],[81.039,14.819],[99.132,-6.304],[24.595,-74.506],[-185.981,3.58]],"v":[[-308.29,37.158],[-220.429,53.013],[-221.476,93.623],[-217.211,121.737],[-10.686,104.233],[294.169,76.562],[7.763,-136.537]],"c":true}]},{"i":{"x":0.833,"y":0.833},"o":{"x":0.167,"y":0.167},"n":"0p833_0p833_0p167_0p167","t":0,"s":[{"i":[[-13.199,-34.681],[-72.854,8.356],[27.35,-0.653],[-26.757,-7.597],[-99.131,6.303],[-24.595,74.506],[177,-3.407]],"o":[[1.183,3.108],[6.238,26.404],[-27.651,1.02],[81.039,14.819],[99.132,-6.304],[24.595,-74.506],[-185.981,3.58]],"v":[[-308.29,37.158],[-220.429,53.013],[-221.476,93.623],[-217.211,121.737],[-10.686,104.233],[294.169,76.562],[7.763,-136.537]],"c":true}],"e":[{"i":[[1.702,-69.611],[-72.89,-8.035],[26.812,5.438],[-24.401,-13.351],[-96.903,21.829],[-5.613,78.259],[137,-20.407]],"o":[[-0.081,3.324],[0.217,27.13],[-18.543,-5.747],[75.723,32.449],[98.449,-22.177],[5.595,-78.006],[-195.08,29.058]],"v":[[-308.438,6.168],[-226.819,30.865],[-230.693,69.803],[-232.28,102.161],[67.314,101.233],[295.169,30.563],[89.763,-134.537]],"c":true}]},{"i":{"x":0.833,"y":0.833},"o":{"x":0.167,"y":0.167},"n":"0p833_0p833_0p167_0p167","t":6,"s":[{"i":[[1.702,-69.611],[-72.89,-8.035],[26.812,5.438],[-24.401,-13.351],[-96.903,21.829],[-5.613,78.259],[137,-20.407]],"o":[[-0.081,3.324],[0.217,27.13],[-18.543,-5.747],[75.723,32.449],[98.449,-22.177],[5.595,-78.006],[-195.08,29.058]],"v":[[-308.438,6.168],[-226.819,30.865],[-230.693,69.803],[-232.28,102.161],[67.314,101.233],[295.169,30.563],[89.763,-134.537]],"c":true}],"e":[{"i":[[14.726,-68.446],[-69.448,-23.548],[20.643,7.215],[-22.71,-14.528],[-99.551,27.823],[0.595,87.494],[173.423,-26.318]],"o":[[-0.699,3.251],[-5.632,26.54],[-24.857,-3.285],[68.79,44.472],[95.666,-26.737],[-0.595,-87.578],[-195,29.593]],"v":[[-304.962,-25.498],[-226.876,16.278],[-235.38,50.341],[-238.526,81.584],[104.315,109.233],[295.169,3.563],[54.764,-113.537]],"c":true}]},{"i":{"x":0.833,"y":0.833},"o":{"x":0.167,"y":0.167},"n":"0p833_0p833_0p167_0p167","t":10,"s":[{"i":[[14.726,-68.446],[-69.448,-23.548],[20.643,7.215],[-22.71,-14.528],[-99.551,27.823],[0.595,87.494],[173.423,-26.318]],"o":[[-0.699,3.251],[-5.632,26.54],[-24.857,-3.285],[68.79,44.472],[95.666,-26.737],[-0.595,-87.578],[-195,29.593]],"v":[[-304.962,-25.498],[-226.876,16.278],[-235.38,50.341],[-238.526,81.584],[104.315,109.233],[295.169,3.563],[54.764,-113.537]],"c":true}],"e":[{"i":[[15.536,-71.787],[-69.184,-24.314],[24.887,11.362],[-20.749,-18.524],[-107.551,17.823],[7.164,96.263],[173.91,-11.326]],"o":[[-0.703,3.25],[-5.925,26.476],[-16.094,-6.246],[66.42,48.736],[97.996,-16.24],[-7.405,-99.506],[-195.916,12.76]],"v":[[-302.773,-36.156],[-225.769,7.43],[-236.143,42.803],[-244.59,70.955],[101.314,117.233],[295.169,-19.438],[36.68,-100.703]],"c":true}]},{"i":{"x":0.833,"y":0.833},"o":{"x":0.167,"y":0.167},"n":"0p833_0p833_0p167_0p167","t":12,"s":[{"i":[[15.536,-71.787],[-69.184,-24.314],[24.887,11.362],[-20.749,-18.524],[-107.551,17.823],[7.164,96.263],[173.91,-11.326]],"o":[[-0.703,3.25],[-5.925,26.476],[-16.094,-6.246],[66.42,48.736],[97.996,-16.24],[-7.405,-99.506],[-195.916,12.76]],"v":[[-302.773,-36.156],[-225.769,7.43],[-236.143,42.803],[-244.59,70.955],[101.314,117.233],[295.169,-19.438],[36.68,-100.703]],"c":true}],"e":[{"i":[[12.91,-60.247],[-71.082,-18.027],[25.804,9.09],[-15.748,-13.181],[-101.551,2.823],[7.959,95.164],[170.816,6.556]],"o":[[-0.697,3.251],[-3.533,26.9],[-17.732,-6.383],[70.252,46.319],[102.735,-2.856],[-8.405,-100.506],[-195.497,-7.892]],"v":[[-302.647,-48.196],[-231.686,-4.854],[-242.004,31.939],[-248.988,60.238],[75.315,130.234],[292.169,-6.438],[2.264,-92.537]],"c":true}]},{"i":{"x":0.833,"y":0.833},"o":{"x":0.167,"y":0.167},"n":"0p833_0p833_0p167_0p167","t":16,"s":[{"i":[[12.91,-60.247],[-71.082,-18.027],[25.804,9.09],[-15.748,-13.181],[-101.551,2.823],[7.959,95.164],[170.816,6.556]],"o":[[-0.697,3.251],[-3.533,26.9],[-17.732,-6.383],[70.252,46.319],[102.735,-2.856],[-8.405,-100.506],[-195.497,-7.892]],"v":[[-302.647,-48.196],[-231.686,-4.854],[-242.004,31.939],[-248.988,60.238],[75.315,130.234],[292.169,-6.438],[2.264,-92.537]],"c":true}],"e":[{"i":[[2.462,-30.476],[-72.095,-13.412],[26.336,7.409],[-23.345,-15.121],[-111.551,-15.177],[-2.352,78.425],[166.52,26.325]],"o":[[-0.268,3.314],[-1.793,27.071],[-19.774,-6.376],[73.111,37.969],[86.944,11.829],[2.595,-86.506],[-195.5,-30.907]],"v":[[-307.699,-33.468],[-237.415,10.289],[-241.462,48.933],[-245.644,77.059],[51.315,139.233],[286.338,26.563],[-15.237,-106.537]],"c":true}]},{"i":{"x":0.833,"y":0.833},"o":{"x":0.167,"y":0.167},"n":"0p833_0p833_0p167_0p167","t":22,"s":[{"i":[[2.462,-30.476],[-72.095,-13.412],[26.336,7.409],[-23.345,-15.121],[-111.551,-15.177],[-2.352,78.425],[166.52,26.325]],"o":[[-0.268,3.314],[-1.793,27.071],[-19.774,-6.376],[73.111,37.969],[86.944,11.829],[2.595,-86.506],[-195.5,-30.907]],"v":[[-307.699,-33.468],[-237.415,10.289],[-241.462,48.933],[-245.644,77.059],[51.315,139.233],[286.338,26.563],[-15.237,-106.537]],"c":true}],"e":[{"i":[[-13.199,-34.681],[-72.854,8.356],[27.35,-0.653],[-26.757,-7.597],[-99.131,6.303],[-24.595,74.506],[177,-3.407]],"o":[[1.183,3.108],[6.238,26.404],[-27.651,1.02],[81.039,14.819],[99.132,-6.304],[24.595,-74.506],[-185.981,3.58]],"v":[[-308.29,37.158],[-220.429,53.013],[-221.476,93.623],[-217.211,121.737],[-10.686,104.233],[294.169,76.562],[7.763,-136.537]],"c":true}]},{"i":{"x":0.833,"y":0.833},"o":{"x":0.167,"y":0.167},"n":"0p833_0p833_0p167_0p167","t":30,"s":[{"i":[[-13.199,-34.681],[-72.854,8.356],[27.35,-0.653],[-26.757,-7.597],[-99.131,6.303],[-24.595,74.506],[177,-3.407]],"o":[[1.183,3.108],[6.238,26.404],[-27.651,1.02],[81.039,14.819],[99.132,-6.304],[24.595,-74.506],[-185.981,3.58]],"v":[[-308.29,37.158],[-220.429,53.013],[-221.476,93.623],[-217.211,121.737],[-10.686,104.233],[294.169,76.562],[7.763,-136.537]],"c":true}],"e":[{"i":[[1.702,-69.611],[-72.89,-8.035],[26.812,5.438],[-24.401,-13.351],[-96.903,21.829],[-5.613,78.259],[137,-20.407]],"o":[[-0.081,3.324],[0.217,27.13],[-18.543,-5.747],[75.723,32.449],[98.449,-22.177],[5.595,-78.006],[-195.08,29.058]],"v":[[-308.438,6.168],[-226.819,30.865],[-230.693,69.803],[-232.28,102.161],[67.314,101.233],[295.169,30.562],[89.763,-134.537]],"c":true}]},{"i":{"x":0.833,"y":0.833},"o":{"x":0.167,"y":0.167},"n":"0p833_0p833_0p167_0p167","t":36,"s":[{"i":[[1.702,-69.611],[-72.89,-8.035],[26.812,5.438],[-24.401,-13.351],[-96.903,21.829],[-5.613,78.259],[137,-20.407]],"o":[[-0.081,3.324],[0.217,27.13],[-18.543,-5.747],[75.723,32.449],[98.449,-22.177],[5.595,-78.006],[-195.08,29.058]],"v":[[-308.438,6.168],[-226.819,30.865],[-230.693,69.803],[-232.28,102.161],[67.314,101.233],[295.169,30.562],[89.763,-134.537]],"c":true}],"e":[{"i":[[14.726,-68.446],[-69.448,-23.548],[20.643,7.215],[-22.71,-14.528],[-99.551,27.823],[0.595,87.494],[173.423,-26.318]],"o":[[-0.699,3.251],[-5.632,26.54],[-24.857,-3.285],[68.79,44.472],[95.666,-26.737],[-0.595,-87.578],[-195,29.593]],"v":[[-304.962,-25.498],[-226.876,16.278],[-235.38,50.341],[-238.526,81.584],[104.315,109.233],[295.169,3.563],[54.764,-113.537]],"c":true}]},{"i":{"x":0.833,"y":0.833},"o":{"x":0.167,"y":0.167},"n":"0p833_0p833_0p167_0p167","t":40,"s":[{"i":[[14.726,-68.446],[-69.448,-23.548],[20.643,7.215],[-22.71,-14.528],[-99.551,27.823],[0.595,87.494],[173.423,-26.318]],"o":[[-0.699,3.251],[-5.632,26.54],[-24.857,-3.285],[68.79,44.472],[95.666,-26.737],[-0.595,-87.578],[-195,29.593]],"v":[[-304.962,-25.498],[-226.876,16.278],[-235.38,50.341],[-238.526,81.584],[104.315,109.233],[295.169,3.563],[54.764,-113.537]],"c":true}],"e":[{"i":[[15.536,-71.787],[-69.184,-24.314],[24.887,11.362],[-20.749,-18.524],[-107.551,17.823],[7.164,96.263],[173.91,-11.326]],"o":[[-0.703,3.25],[-5.925,26.476],[-16.094,-6.246],[66.42,48.736],[97.996,-16.24],[-7.405,-99.506],[-195.916,12.76]],"v":[[-302.773,-36.156],[-225.769,7.43],[-236.143,42.803],[-244.59,70.955],[101.314,117.233],[295.169,-19.438],[36.68,-100.703]],"c":true}]},{"i":{"x":0.833,"y":0.833},"o":{"x":0.167,"y":0.167},"n":"0p833_0p833_0p167_0p167","t":42,"s":[{"i":[[15.536,-71.787],[-69.184,-24.314],[24.887,11.362],[-20.749,-18.524],[-107.551,17.823],[7.164,96.263],[173.91,-11.326]],"o":[[-0.703,3.25],[-5.925,26.476],[-16.094,-6.246],[66.42,48.736],[97.996,-16.24],[-7.405,-99.506],[-195.916,12.76]],"v":[[-302.773,-36.156],[-225.769,7.43],[-236.143,42.803],[-244.59,70.955],[101.314,117.233],[295.169,-19.438],[36.68,-100.703]],"c":true}],"e":[{"i":[[12.91,-60.247],[-71.082,-18.027],[25.804,9.09],[-15.748,-13.181],[-101.551,2.823],[7.959,95.164],[170.816,6.556]],"o":[[-0.697,3.251],[-3.533,26.9],[-17.732,-6.383],[70.252,46.319],[102.735,-2.856],[-8.405,-100.506],[-195.497,-7.892]],"v":[[-302.647,-48.196],[-231.686,-4.854],[-242.004,31.939],[-248.988,60.238],[75.315,130.233],[292.169,-6.438],[2.264,-92.537]],"c":true}]},{"i":{"x":0.833,"y":0.833},"o":{"x":0.167,"y":0.167},"n":"0p833_0p833_0p167_0p167","t":46,"s":[{"i":[[12.91,-60.247],[-71.082,-18.027],[25.804,9.09],[-15.748,-13.181],[-101.551,2.823],[7.959,95.164],[170.816,6.556]],"o":[[-0.697,3.251],[-3.533,26.9],[-17.732,-6.383],[70.252,46.319],[102.735,-2.856],[-8.405,-100.506],[-195.497,-7.892]],"v":[[-302.647,-48.196],[-231.686,-4.854],[-242.004,31.939],[-248.988,60.238],[75.315,130.233],[292.169,-6.438],[2.264,-92.537]],"c":true}],"e":[{"i":[[2.462,-30.476],[-72.095,-13.412],[26.336,7.409],[-23.345,-15.121],[-111.551,-15.177],[-2.352,78.425],[166.519,26.325]],"o":[[-0.268,3.314],[-1.793,27.071],[-19.774,-6.376],[73.111,37.969],[86.944,11.829],[2.595,-86.506],[-195.5,-30.907]],"v":[[-307.699,-33.468],[-237.415,10.289],[-241.462,48.933],[-245.644,77.059],[51.315,139.233],[286.338,26.563],[-15.237,-106.537]],"c":true}]},{"i":{"x":0.833,"y":0.833},"o":{"x":0.167,"y":0.167},"n":"0p833_0p833_0p167_0p167","t":52,"s":[{"i":[[2.462,-30.476],[-72.095,-13.412],[26.336,7.409],[-23.345,-15.121],[-111.551,-15.177],[-2.352,78.425],[166.519,26.325]],"o":[[-0.268,3.314],[-1.793,27.071],[-19.774,-6.376],[73.111,37.969],[86.944,11.829],[2.595,-86.506],[-195.5,-30.907]],"v":[[-307.699,-33.468],[-237.415,10.289],[-241.462,48.933],[-245.644,77.059],[51.315,139.233],[286.338,26.563],[-15.237,-106.537]],"c":true}],"e":[{"i":[[-13.199,-34.681],[-72.854,8.356],[27.35,-0.653],[-26.757,-7.597],[-99.131,6.303],[-24.595,74.506],[177,-3.407]],"o":[[1.183,3.108],[6.238,26.404],[-27.651,1.02],[81.039,14.819],[99.132,-6.304],[24.595,-74.506],[-185.981,3.58]],"v":[[-308.29,37.158],[-220.429,53.013],[-221.476,93.623],[-217.211,121.737],[-10.686,104.233],[294.169,76.562],[7.763,-136.537]],"c":true}]},{"t":60}]},"nm":"Path 2","mn":"ADBE Vector Shape - Group"},{"ty":"gf","o":{"a":0,"k":100},"r":1,"g":{"p":3,"k":{"a":0,"k":[0,1,0.824,0.129,0.5,0.998,0.582,0.48,1,0.996,0.341,0.831]}},"s":{"a":0,"k":[-298,-13]},"e":{"a":0,"k":[288,-3]},"t":1,"nm":"Gradient Fill 1","mn":"ADBE Vector Graphic - G-Fill"},{"ty":"tr","p":{"a":0,"k":[475.236,510.944],"ix":2},"a":{"a":0,"k":[0,0],"ix":1},"s":{"a":0,"k":[100,100],"ix":3},"r":{"a":0,"k":0,"ix":6},"o":{"a":0,"k":100,"ix":7},"sk":{"a":0,"k":0,"ix":4},"sa":{"a":0,"k":0,"ix":5},"nm":"Transform"}],"nm":"Group 1","np":2,"cix":2,"ix":1,"mn":"ADBE Vector Group"}],"ip":-51,"op":153,"st":0,"bm":0,"sr":1},{"ddd":0,"ind":17,"ty":4,"nm":"Body","hd":true,"ks":{"o":{"a":0,"k":100},"r":{"a":0,"k":0},"p":{"a":0,"k":[500,500,0]},"a":{"a":0,"k":[500,500,0]},"s":{"a":0,"k":[100,100,100]}},"ao":0,"shapes":[{"ty":"gr","it":[{"ind":0,"ty":"sh","ix":1,"ks":{"a":1,"k":[{"i":{"x":0.667,"y":1},"o":{"x":0.167,"y":0.167},"n":"0p667_1_0p167_0p167","t":-16,"s":[{"i":[[0,-37.108],[-71.062,-18.104],[25.794,9.118],[-22.305,-16.618],[-99.131,6.303],[0.679,62.494],[175.394,2.27]],"o":[[0,3.325],[-3.562,26.896],[-26.206,-8.882],[70.468,42.675],[99.132,-6.304],[-4.321,-28.506],[-186,-2.407]],"v":[[-304.084,-28.266],[-226.674,18.16],[-241.03,52.938],[-247.044,80.73],[14.315,127.233],[303.084,-5.438],[-28.236,-133.537]],"c":true}],"e":[{"i":[[-13.199,-34.681],[-72.854,8.356],[27.35,-0.653],[-26.757,-7.597],[-99.131,6.303],[-24.595,74.506],[175.394,2.27]],"o":[[1.183,3.108],[6.238,26.404],[-27.651,1.02],[81.039,14.819],[99.132,-6.304],[24.595,-74.506],[-186,-2.407]],"v":[[-309.29,40.158],[-220.429,56.013],[-221.476,93.623],[-217.211,121.737],[-10.686,104.233],[294.169,76.562],[-10.236,-139.537]],"c":true}]},{"i":{"x":0.833,"y":0.833},"o":{"x":0.333,"y":0.091},"n":"0p833_0p833_0p333_0p091","t":0,"s":[{"i":[[-13.199,-34.681],[-72.854,8.356],[27.35,-0.653],[-26.757,-7.597],[-99.131,6.303],[-24.595,74.506],[175.394,2.27]],"o":[[1.183,3.108],[6.238,26.404],[-27.651,1.02],[81.039,14.819],[99.132,-6.304],[24.595,-74.506],[-186,-2.407]],"v":[[-309.29,40.158],[-220.429,56.013],[-221.476,93.623],[-217.211,121.737],[-10.686,104.233],[294.169,76.562],[-10.236,-139.537]],"c":true}],"e":[{"i":[[19.47,-57.904],[-60.115,-27.333],[21.416,12.179],[-17.132,-18.272],[-98.385,12.596],[-9.797,67.473],[215.505,-36.293]],"o":[[-0.478,2.977],[-7.429,23.275],[-21.819,-12.035],[55.686,49.018],[155.925,-22.623],[8.201,-62.211],[-215.505,36.293]],"v":[[-293.802,-36.396],[-232.558,17.05],[-250.806,45.597],[-260.551,69.277],[0.623,125.311],[301.022,8.549],[13.268,-99.237]],"c":true}]},{"i":{"x":0.386,"y":0.836},"o":{"x":0.167,"y":0.167},"n":"0p386_0p836_0p167_0p167","t":7,"s":[{"i":[[19.47,-57.904],[-60.115,-27.333],[21.416,12.179],[-17.132,-18.272],[-98.385,12.596],[-9.797,67.473],[215.505,-36.293]],"o":[[-0.478,2.977],[-7.429,23.275],[-21.819,-12.035],[55.686,49.018],[155.925,-22.623],[8.201,-62.211],[-215.505,36.293]],"v":[[-293.802,-36.396],[-232.558,17.05],[-250.806,45.597],[-260.551,69.277],[0.623,125.311],[301.022,8.549],[13.268,-99.237]],"c":true}],"e":[{"i":[[42.6,-74.347],[-51.095,-52.601],[17.214,21.264],[-10.318,-25.831],[-97.857,17.052],[0.679,62.494],[217.938,-31.759]],"o":[[-1.653,2.885],[-17.105,21.06],[-17.689,-21.278],[37.736,73.232],[196.134,-34.177],[-3.405,-53.506],[-141.315,20.593]],"v":[[-282.836,-90.597],[-241.146,-10.537],[-271.573,11.594],[-291.236,32.135],[8.629,140.233],[303.169,-63.438],[37.078,-78.537]],"c":true}]},{"i":{"x":0.833,"y":0.833},"o":{"x":0.709,"y":0.193},"n":"0p833_0p833_0p709_0p193","t":15,"s":[{"i":[[42.6,-74.347],[-51.095,-52.601],[17.214,21.264],[-10.318,-25.831],[-97.857,17.052],[0.679,62.494],[217.938,-31.759]],"o":[[-1.653,2.885],[-17.105,21.06],[-17.689,-21.278],[37.736,73.232],[196.134,-34.177],[-3.405,-53.506],[-141.315,20.593]],"v":[[-282.836,-90.597],[-241.146,-10.537],[-271.573,11.594],[-291.236,32.135],[8.629,140.233],[303.169,-63.438],[37.078,-78.537]],"c":true}],"e":[{"i":[[17.552,-56.541],[-60.863,-25.238],[21.764,11.425],[-17.697,-17.646],[-169.805,-15.983],[-1.983,49.28],[164.36,23.575]],"o":[[-0.38,2.985],[-6.626,23.459],[-22.161,-11.268],[57.174,47.011],[169.805,15.983],[-4.983,-65.72],[-164.36,-23.575]],"v":[[-294.711,-31.902],[-231.846,19.337],[-249.084,48.417],[-258.006,72.357],[-0.041,124.073],[301.747,5.777],[-7.877,-107.368]],"c":true}]},{"i":{"x":0.667,"y":1},"o":{"x":0.167,"y":0.167},"n":"0p667_1_0p167_0p167","t":23,"s":[{"i":[[17.552,-56.541],[-60.863,-25.238],[21.764,11.425],[-17.697,-17.646],[-169.805,-15.983],[-1.983,49.28],[164.36,23.575]],"o":[[-0.38,2.985],[-6.626,23.459],[-22.161,-11.268],[57.174,47.011],[169.805,15.983],[-4.983,-65.72],[-164.36,-23.575]],"v":[[-294.711,-31.902],[-231.846,19.337],[-249.084,48.417],[-258.006,72.357],[-0.041,124.073],[301.747,5.777],[-7.877,-107.368]],"c":true}],"e":[{"i":[[-13.199,-34.681],[-72.854,8.356],[27.35,-0.653],[-26.757,-7.597],[-99.131,6.303],[-24.595,74.506],[175.394,2.27]],"o":[[1.183,3.108],[6.238,26.404],[-27.651,1.02],[81.039,14.819],[99.132,-6.304],[24.595,-74.506],[-186,-2.407]],"v":[[-309.29,40.158],[-220.429,56.013],[-221.476,93.623],[-217.211,121.737],[-10.686,104.233],[294.169,76.562],[-10.236,-139.537]],"c":true}]},{"i":{"x":0.833,"y":0.833},"o":{"x":0.333,"y":0.091},"n":"0p833_0p833_0p333_0p091","t":29,"s":[{"i":[[-13.199,-34.681],[-72.854,8.356],[27.35,-0.653],[-26.757,-7.597],[-99.131,6.303],[-24.595,74.506],[175.394,2.27]],"o":[[1.183,3.108],[6.238,26.404],[-27.651,1.02],[81.039,14.819],[99.132,-6.304],[24.595,-74.506],[-186,-2.407]],"v":[[-309.29,40.158],[-220.429,56.013],[-221.476,93.623],[-217.211,121.737],[-10.686,104.233],[294.169,76.562],[-10.236,-139.537]],"c":true}],"e":[{"i":[[19.47,-57.904],[-60.115,-27.333],[21.416,12.179],[-17.132,-18.273],[-98.385,12.596],[-9.797,67.473],[215.505,-36.293]],"o":[[-0.478,2.977],[-7.429,23.275],[-21.819,-12.035],[55.686,49.018],[155.925,-22.623],[8.201,-62.211],[-215.505,36.293]],"v":[[-293.802,-36.396],[-232.558,17.05],[-250.806,45.597],[-260.551,69.277],[0.623,125.311],[301.022,8.549],[13.268,-99.237]],"c":true}]},{"i":{"x":0.386,"y":0.836},"o":{"x":0.167,"y":0.167},"n":"0p386_0p836_0p167_0p167","t":36,"s":[{"i":[[19.47,-57.904],[-60.115,-27.333],[21.416,12.179],[-17.132,-18.273],[-98.385,12.596],[-9.797,67.473],[215.505,-36.293]],"o":[[-0.478,2.977],[-7.429,23.275],[-21.819,-12.035],[55.686,49.018],[155.925,-22.623],[8.201,-62.211],[-215.505,36.293]],"v":[[-293.802,-36.396],[-232.558,17.05],[-250.806,45.597],[-260.551,69.277],[0.623,125.311],[301.022,8.549],[13.268,-99.237]],"c":true}],"e":[{"i":[[42.6,-74.347],[-51.095,-52.601],[17.214,21.264],[-10.318,-25.831],[-97.857,17.052],[0.679,62.494],[217.938,-31.759]],"o":[[-1.653,2.885],[-17.105,21.06],[-17.689,-21.278],[37.736,73.232],[196.134,-34.177],[-3.405,-53.506],[-141.315,20.593]],"v":[[-282.836,-90.597],[-241.146,-10.537],[-271.573,11.594],[-291.236,32.135],[8.629,140.233],[303.169,-63.438],[37.078,-78.537]],"c":true}]},{"i":{"x":0.833,"y":0.833},"o":{"x":0.709,"y":0.193},"n":"0p833_0p833_0p709_0p193","t":44,"s":[{"i":[[42.6,-74.347],[-51.095,-52.601],[17.214,21.264],[-10.318,-25.831],[-97.857,17.052],[0.679,62.494],[217.938,-31.759]],"o":[[-1.653,2.885],[-17.105,21.06],[-17.689,-21.278],[37.736,73.232],[196.134,-34.177],[-3.405,-53.506],[-141.315,20.593]],"v":[[-282.836,-90.597],[-241.146,-10.537],[-271.573,11.594],[-291.236,32.135],[8.629,140.233],[303.169,-63.438],[37.078,-78.537]],"c":true}],"e":[{"i":[[17.552,-56.541],[-60.863,-25.238],[21.764,11.425],[-17.697,-17.646],[-169.805,-15.983],[-1.983,49.28],[164.36,23.575]],"o":[[-0.38,2.985],[-6.626,23.459],[-22.161,-11.268],[57.174,47.011],[169.805,15.983],[-4.983,-65.72],[-164.36,-23.575]],"v":[[-294.711,-31.902],[-231.846,19.337],[-249.084,48.417],[-258.006,72.357],[-0.041,124.073],[301.747,5.777],[-7.877,-107.368]],"c":true}]},{"i":{"x":0.667,"y":1},"o":{"x":0.167,"y":0.167},"n":"0p667_1_0p167_0p167","t":52,"s":[{"i":[[17.552,-56.541],[-60.863,-25.238],[21.764,11.425],[-17.697,-17.646],[-169.805,-15.983],[-1.983,49.28],[164.36,23.575]],"o":[[-0.38,2.985],[-6.626,23.459],[-22.161,-11.268],[57.174,47.011],[169.805,15.983],[-4.983,-65.72],[-164.36,-23.575]],"v":[[-294.711,-31.902],[-231.846,19.337],[-249.084,48.417],[-258.006,72.357],[-0.041,124.073],[301.747,5.777],[-7.877,-107.368]],"c":true}],"e":[{"i":[[-13.199,-34.681],[-72.854,8.356],[27.35,-0.653],[-26.757,-7.597],[-99.131,6.303],[-24.595,74.506],[175.394,2.27]],"o":[[1.183,3.108],[6.238,26.404],[-27.651,1.02],[81.039,14.819],[99.132,-6.304],[24.595,-74.506],[-186,-2.407]],"v":[[-309.29,40.158],[-220.429,56.013],[-221.476,93.623],[-217.211,121.737],[-10.686,104.233],[294.169,76.562],[-10.236,-139.537]],"c":true}]},{"i":{"x":0.833,"y":0.833},"o":{"x":0.333,"y":0.091},"n":"0p833_0p833_0p333_0p091","t":58,"s":[{"i":[[-13.199,-34.681],[-72.854,8.356],[27.35,-0.653],[-26.757,-7.597],[-99.131,6.303],[-24.595,74.506],[175.394,2.27]],"o":[[1.183,3.108],[6.238,26.404],[-27.651,1.02],[81.039,14.819],[99.132,-6.304],[24.595,-74.506],[-186,-2.407]],"v":[[-309.29,40.158],[-220.429,56.013],[-221.476,93.623],[-217.211,121.737],[-10.686,104.233],[294.169,76.562],[-10.236,-139.537]],"c":true}],"e":[{"i":[[19.47,-57.904],[-60.115,-27.333],[21.416,12.179],[-17.132,-18.273],[-98.385,12.596],[-9.797,67.473],[215.505,-36.293]],"o":[[-0.478,2.977],[-7.429,23.275],[-21.819,-12.035],[55.686,49.018],[155.925,-22.623],[8.201,-62.211],[-215.505,36.293]],"v":[[-293.802,-36.396],[-232.558,17.05],[-250.806,45.597],[-260.551,69.277],[0.623,125.311],[301.022,8.549],[13.268,-99.237]],"c":true}]},{"i":{"x":0.386,"y":0.836},"o":{"x":0.167,"y":0.167},"n":"0p386_0p836_0p167_0p167","t":65,"s":[{"i":[[19.47,-57.904],[-60.115,-27.333],[21.416,12.179],[-17.132,-18.273],[-98.385,12.596],[-9.797,67.473],[215.505,-36.293]],"o":[[-0.478,2.977],[-7.429,23.275],[-21.819,-12.035],[55.686,49.018],[155.925,-22.623],[8.201,-62.211],[-215.505,36.293]],"v":[[-293.802,-36.396],[-232.558,17.05],[-250.806,45.597],[-260.551,69.277],[0.623,125.311],[301.022,8.549],[13.268,-99.237]],"c":true}],"e":[{"i":[[42.6,-74.347],[-51.095,-52.601],[17.214,21.264],[-10.318,-25.831],[-97.857,17.052],[0.679,62.494],[217.938,-31.759]],"o":[[-1.653,2.885],[-17.105,21.06],[-17.689,-21.278],[37.736,73.232],[196.134,-34.177],[-3.405,-53.506],[-141.315,20.593]],"v":[[-282.836,-90.597],[-241.146,-10.537],[-271.573,11.594],[-291.236,32.135],[8.629,140.233],[303.169,-63.438],[37.078,-78.537]],"c":true}]},{"i":{"x":0.833,"y":0.833},"o":{"x":0.709,"y":0.193},"n":"0p833_0p833_0p709_0p193","t":73,"s":[{"i":[[42.6,-74.347],[-51.095,-52.601],[17.214,21.264],[-10.318,-25.831],[-97.857,17.052],[0.679,62.494],[217.938,-31.759]],"o":[[-1.653,2.885],[-17.105,21.06],[-17.689,-21.278],[37.736,73.232],[196.134,-34.177],[-3.405,-53.506],[-141.315,20.593]],"v":[[-282.836,-90.597],[-241.146,-10.537],[-271.573,11.594],[-291.236,32.135],[8.629,140.233],[303.169,-63.438],[37.078,-78.537]],"c":true}],"e":[{"i":[[17.552,-56.541],[-60.863,-25.238],[21.764,11.425],[-17.697,-17.646],[-169.805,-15.983],[-1.983,49.28],[164.36,23.575]],"o":[[-0.38,2.985],[-6.626,23.459],[-22.161,-11.268],[57.174,47.011],[169.805,15.983],[-4.983,-65.72],[-164.36,-23.575]],"v":[[-294.711,-31.902],[-231.846,19.337],[-249.084,48.417],[-258.006,72.357],[-0.041,124.073],[301.747,5.777],[-7.877,-107.368]],"c":true}]},{"i":{"x":0.605,"y":0.895},"o":{"x":0.167,"y":0.167},"n":"0p605_0p895_0p167_0p167","t":81,"s":[{"i":[[17.552,-56.541],[-60.863,-25.238],[21.764,11.425],[-17.697,-17.646],[-169.805,-15.983],[-1.983,49.28],[164.36,23.575]],"o":[[-0.38,2.985],[-6.626,23.459],[-22.161,-11.268],[57.174,47.011],[169.805,15.983],[-4.983,-65.72],[-164.36,-23.575]],"v":[[-294.711,-31.902],[-231.846,19.337],[-249.084,48.417],[-258.006,72.357],[-0.041,124.073],[301.747,5.777],[-7.877,-107.368]],"c":true}],"e":[{"i":[[-13.199,-34.681],[-72.854,8.356],[27.35,-0.653],[-26.757,-7.597],[-99.131,6.303],[-24.595,74.506],[175.394,2.27]],"o":[[1.183,3.108],[6.238,26.404],[-27.651,1.02],[81.039,14.819],[99.132,-6.304],[24.595,-74.506],[-186,-2.407]],"v":[[-309.29,40.158],[-220.429,56.013],[-221.476,93.623],[-217.211,121.737],[-10.686,104.234],[299.169,59.562],[-26.236,-141.537]],"c":true}]},{"t":87}]},"nm":"Path 2","mn":"ADBE Vector Shape - Group"},{"ty":"gf","o":{"a":0,"k":100},"r":1,"g":{"p":3,"k":{"a":0,"k":[0,1,0.824,0.129,0.5,0.998,0.582,0.48,1,0.996,0.341,0.831]}},"s":{"a":0,"k":[-298,-13]},"e":{"a":0,"k":[288,-3]},"t":1,"nm":"Gradient Fill 1","mn":"ADBE Vector Graphic - G-Fill"},{"ty":"tr","p":{"a":0,"k":[475.236,510.944],"ix":2},"a":{"a":0,"k":[0,0],"ix":1},"s":{"a":0,"k":[100,100],"ix":3},"r":{"a":0,"k":0,"ix":6},"o":{"a":0,"k":100,"ix":7},"sk":{"a":0,"k":0,"ix":4},"sa":{"a":0,"k":0,"ix":5},"nm":"Transform"}],"nm":"Group 1","np":2,"cix":2,"ix":1,"mn":"ADBE Vector Group"}],"ip":-51,"op":153,"st":0,"bm":0,"sr":1},{"ddd":0,"ind":18,"ty":4,"nm":"Tail Outlines","ks":{"o":{"a":0,"k":100},"r":{"a":1,"k":[{"i":{"x":[0.667],"y":[1]},"o":{"x":[0.333],"y":[0]},"n":["0p667_1_0p333_0"],"t":-25,"s":[37],"e":[-24]},{"i":{"x":[0.667],"y":[1]},"o":{"x":[0.333],"y":[0]},"n":["0p667_1_0p333_0"],"t":-10,"s":[-24],"e":[37]},{"i":{"x":[0.667],"y":[1]},"o":{"x":[0.333],"y":[0]},"n":["0p667_1_0p333_0"],"t":5,"s":[37],"e":[-24]},{"i":{"x":[0.667],"y":[1]},"o":{"x":[0.333],"y":[0]},"n":["0p667_1_0p333_0"],"t":20,"s":[-24],"e":[37]},{"i":{"x":[0.667],"y":[1]},"o":{"x":[0.333],"y":[0]},"n":["0p667_1_0p333_0"],"t":35,"s":[37],"e":[-24]},{"i":{"x":[0.667],"y":[1]},"o":{"x":[0.333],"y":[0]},"n":["0p667_1_0p333_0"],"t":50,"s":[-24],"e":[37]},{"t":65}]},"p":{"a":1,"k":[{"i":{"x":0.39,"y":1},"o":{"x":0.333,"y":0},"n":"0p39_1_0p333_0","t":0,"s":[734,570.5,0],"e":[754,476,0],"to":[0,0,0],"ti":[0,0,0]},{"i":{"x":0.667,"y":1},"o":{"x":0.359,"y":0},"n":"0p667_1_0p359_0","t":13,"s":[754,476,0],"e":[734,570.5,0],"to":[0,0,0],"ti":[0,0,0]},{"i":{"x":0.39,"y":1},"o":{"x":0.333,"y":0},"n":"0p39_1_0p333_0","t":30,"s":[734,570.5,0],"e":[754,476,0],"to":[0,0,0],"ti":[0,0,0]},{"i":{"x":0.246,"y":1},"o":{"x":0.359,"y":0},"n":"0p246_1_0p359_0","t":43,"s":[754,476,0],"e":[734,570.5,0],"to":[0,0,0],"ti":[0,0,0]},{"t":60}]},"a":{"a":0,"k":[729,508,0]},"s":{"a":0,"k":[100,100,100]}},"ao":0,"shapes":[{"ty":"gr","it":[{"ind":0,"ty":"sh","ix":1,"ks":{"a":0,"k":{"i":[[8.142,0],[0,0],[-8.142,0],[0,0]],"o":[[0,0],[-8.128,0],[0,0],[8.129,0]],"v":[[12.238,-6.316],[-12.238,-6.316],[-12.238,6.316],[12.238,6.316]],"c":true}},"nm":"Path 1","mn":"ADBE Vector Shape - Group"},{"ty":"fl","c":{"a":0,"k":[0.314,0.314,0.314,1]},"o":{"a":0,"k":100},"r":1,"nm":"Fill 1","mn":"ADBE Vector Graphic - Fill"},{"ty":"tr","p":{"a":0,"k":[822.865,536.011],"ix":2},"a":{"a":0,"k":[0,0],"ix":1},"s":{"a":0,"k":[100,100],"ix":3},"r":{"a":0,"k":0,"ix":6},"o":{"a":0,"k":100,"ix":7},"sk":{"a":0,"k":0,"ix":4},"sa":{"a":0,"k":0,"ix":5},"nm":"Transform"}],"nm":"Group 1","np":2,"cix":2,"ix":1,"mn":"ADBE Vector Group"},{"ty":"gr","it":[{"ind":0,"ty":"sh","ix":1,"ks":{"a":0,"k":{"i":[[8.138,-0.427],[24.537,6.379],[-7.875,-2.046],[-26.383,1.383]],"o":[[-25.314,1.327],[-7.874,-2.046],[25.566,6.646],[8.088,-0.424]],"v":[[38.992,-2.219],[-35.897,-9.751],[-39.255,2.43],[38.992,10.414]],"c":true}},"nm":"Path 1","mn":"ADBE Vector Shape - Group"},{"ty":"fl","c":{"a":0,"k":[0.314,0.314,0.314,1]},"o":{"a":0,"k":100},"r":1,"nm":"Fill 1","mn":"ADBE Vector Graphic - Fill"},{"ty":"tr","p":{"a":0,"k":[815.84,557.013],"ix":2},"a":{"a":0,"k":[0,0],"ix":1},"s":{"a":0,"k":[100,100],"ix":3},"r":{"a":0,"k":0,"ix":6},"o":{"a":0,"k":100,"ix":7},"sk":{"a":0,"k":0,"ix":4},"sa":{"a":0,"k":0,"ix":5},"nm":"Transform"}],"nm":"Group 2","np":2,"cix":2,"ix":2,"mn":"ADBE Vector Group"},{"ty":"gr","it":[{"ind":0,"ty":"sh","ix":1,"ks":{"a":0,"k":{"i":[[7.808,-2.378],[9.341,-1.619],[-7.964,1.381],[-9.069,2.762]],"o":[[-9.068,2.763],[-7.995,1.387],[9.341,-1.62],[7.755,-2.363]],"v":[[12.239,-8.877],[-15.357,-2.308],[-11.998,9.874],[15.597,3.305]],"c":true}},"nm":"Path 1","mn":"ADBE Vector Shape - Group"},{"ty":"fl","c":{"a":0,"k":[0.314,0.314,0.314,1]},"o":{"a":0,"k":100},"r":1,"nm":"Fill 1","mn":"ADBE Vector Graphic - Fill"},{"ty":"tr","p":{"a":0,"k":[816.458,479.616],"ix":2},"a":{"a":0,"k":[0,0],"ix":1},"s":{"a":0,"k":[100,100],"ix":3},"r":{"a":0,"k":0,"ix":6},"o":{"a":0,"k":100,"ix":7},"sk":{"a":0,"k":0,"ix":4},"sa":{"a":0,"k":0,"ix":5},"nm":"Transform"}],"nm":"Group 3","np":2,"cix":2,"ix":3,"mn":"ADBE Vector Group"},{"ty":"gr","it":[{"ind":0,"ty":"sh","ix":1,"ks":{"a":0,"k":{"i":[[8.095,-0.814],[20.405,-6.061],[-7.822,2.323],[-20.047,2.016]],"o":[[-21.176,2.129],[-7.776,2.309],[19.31,-5.735],[8.012,-0.805]],"v":[[31.044,-12.939],[-31.362,-0.752],[-28.005,11.43],[31.044,-0.307]],"c":true}},"nm":"Path 1","mn":"ADBE Vector Shape - Group"},{"ty":"fl","c":{"a":0,"k":[0.314,0.314,0.314,1]},"o":{"a":0,"k":100},"r":1,"nm":"Fill 1","mn":"ADBE Vector Graphic - Fill"},{"ty":"tr","p":{"a":0,"k":[813.549,459.885],"ix":2},"a":{"a":0,"k":[0,0],"ix":1},"s":{"a":0,"k":[100,100],"ix":3},"r":{"a":0,"k":0,"ix":6},"o":{"a":0,"k":100,"ix":7},"sk":{"a":0,"k":0,"ix":4},"sa":{"a":0,"k":0,"ix":5},"nm":"Transform"}],"nm":"Group 4","np":2,"cix":2,"ix":4,"mn":"ADBE Vector Group"},{"ty":"gr","it":[{"ind":0,"ty":"sh","ix":1,"ks":{"a":0,"k":{"i":[[19.688,-7.311],[15.321,-18.663],[-3.69,-13.899],[-19.511,-7.202],[-40.793,12.888],[3.773,22.961],[23.043,-2.236],[4.489,28.723],[27.558,-0.09]],"o":[[-21.687,8.053],[-9.158,11.155],[6.35,23.918],[38.342,14.151],[7.872,-2.487],[-3.773,-22.961],[25.191,-7.542],[-1.983,-12.688],[-33.35,0.109]],"v":[[-43.547,-60.313],[-93.973,-29.681],[-102.965,13.019],[-53.646,48.684],[66.189,65.311],[96.732,29.789],[18.893,-2.385],[93.489,-51.133],[44.328,-79.651]],"c":true}},"nm":"Path 2","mn":"ADBE Vector Shape - Group"},{"ty":"gf","o":{"a":0,"k":100},"r":1,"g":{"p":3,"k":{"a":0,"k":[0,0.035,0.671,0.843,0.5,0.237,0.812,0.865,1,0.439,0.953,0.886]}},"s":{"a":0,"k":[-51,-2]},"e":{"a":0,"k":[87,-12]},"t":1,"nm":"Gradient Fill 1","mn":"ADBE Vector Graphic - G-Fill"},{"ty":"tr","p":{"a":0,"k":[792.297,511.632],"ix":2},"a":{"a":0,"k":[0,0],"ix":1},"s":{"a":0,"k":[100,100],"ix":3},"r":{"a":0,"k":0,"ix":6},"o":{"a":0,"k":100,"ix":7},"sk":{"a":0,"k":0,"ix":4},"sa":{"a":0,"k":0,"ix":5},"nm":"Transform"}],"nm":"Group 5","np":2,"cix":2,"ix":5,"mn":"ADBE Vector Group"}],"ip":0,"op":153,"st":0,"bm":0,"sr":1},{"ddd":0,"ind":19,"ty":2,"nm":"R_Mustasch","hd":true,"refId":"image_0","ks":{"o":{"a":0,"k":100},"r":{"a":0,"k":0},"p":{"a":0,"k":[500,500,0]},"a":{"a":0,"k":[500,500,0]},"s":{"a":0,"k":[100,100,100]}},"ao":0,"ip":0,"op":153,"st":0,"bm":0,"sr":1},{"ddd":0,"ind":20,"ty":2,"nm":"L_Mustasch","hd":true,"refId":"image_1","ks":{"o":{"a":0,"k":100},"r":{"a":0,"k":0},"p":{"a":0,"k":[500,500,0]},"a":{"a":0,"k":[500,500,0]},"s":{"a":0,"k":[100,100,100]}},"ao":0,"ip":0,"op":153,"st":0,"bm":0,"sr":1},{"ddd":0,"ind":21,"ty":2,"nm":"Layer 4","hd":true,"refId":"image_2","ks":{"o":{"a":0,"k":100},"r":{"a":0,"k":0},"p":{"a":0,"k":[500,500,0]},"a":{"a":0,"k":[500,500,0]},"s":{"a":0,"k":[100,100,100]}},"ao":0,"ip":0,"op":153,"st":0,"bm":0,"sr":1},{"ddd":0,"ind":22,"ty":2,"nm":"Fin","hd":true,"refId":"image_3","ks":{"o":{"a":0,"k":100},"r":{"a":0,"k":0},"p":{"a":0,"k":[753,310,0]},"a":{"a":0,"k":[500,500,0]},"s":{"a":0,"k":[100,100,100]}},"ao":0,"ip":0,"op":153,"st":0,"bm":0,"sr":1},{"ddd":0,"ind":23,"ty":2,"nm":"Eye_Closed","hd":true,"refId":"image_4","ks":{"o":{"a":0,"k":100},"r":{"a":0,"k":0},"p":{"a":0,"k":[500,500,0]},"a":{"a":0,"k":[500,500,0]},"s":{"a":0,"k":[100,100,100]}},"ao":0,"ip":0,"op":153,"st":0,"bm":0,"sr":1},{"ddd":0,"ind":24,"ty":2,"nm":"Eye_Mid","hd":true,"refId":"image_5","ks":{"o":{"a":0,"k":100},"r":{"a":0,"k":0},"p":{"a":0,"k":[500,500,0]},"a":{"a":0,"k":[500,500,0]},"s":{"a":0,"k":[100,100,100]}},"ao":0,"ip":0,"op":153,"st":0,"bm":0,"sr":1},{"ddd":0,"ind":25,"ty":2,"nm":"Pupil","hd":true,"refId":"image_6","ks":{"o":{"a":0,"k":100},"r":{"a":0,"k":0},"p":{"a":0,"k":[500,500,0]},"a":{"a":0,"k":[500,500,0]},"s":{"a":0,"k":[100,100,100]}},"ao":0,"ip":0,"op":153,"st":0,"bm":0,"sr":1},{"ddd":0,"ind":26,"ty":2,"nm":"Eye","hd":true,"refId":"image_7","ks":{"o":{"a":0,"k":100},"r":{"a":0,"k":0},"p":{"a":0,"k":[500,500,0]},"a":{"a":0,"k":[500,500,0]},"s":{"a":0,"k":[100,100,100]}},"ao":0,"ip":0,"op":153,"st":0,"bm":0,"sr":1},{"ddd":0,"ind":27,"ty":2,"nm":"Mouth","hd":true,"refId":"image_8","ks":{"o":{"a":0,"k":100},"r":{"a":0,"k":0},"p":{"a":0,"k":[500,500,0]},"a":{"a":0,"k":[500,500,0]},"s":{"a":0,"k":[100,100,100]}},"ao":0,"ip":0,"op":153,"st":0,"bm":0,"sr":1},{"ddd":0,"ind":28,"ty":2,"nm":"Beard","hd":true,"refId":"image_9","ks":{"o":{"a":0,"k":100},"r":{"a":0,"k":0},"p":{"a":0,"k":[500,500,0]},"a":{"a":0,"k":[500,500,0]},"s":{"a":0,"k":[100,100,100]}},"ao":0,"ip":0,"op":153,"st":0,"bm":0,"sr":1},{"ddd":0,"ind":29,"ty":2,"nm":"Layer 1","hd":true,"refId":"image_10","ks":{"o":{"a":0,"k":100},"r":{"a":0,"k":0},"p":{"a":0,"k":[500,214,0]},"a":{"a":0,"k":[500,500,0]},"s":{"a":0,"k":[100,100,100]}},"ao":0,"ip":0,"op":153,"st":0,"bm":0,"sr":1},{"ddd":0,"ind":30,"ty":2,"nm":"Teeth","hd":true,"refId":"image_11","ks":{"o":{"a":0,"k":100},"r":{"a":0,"k":0},"p":{"a":0,"k":[500,500,0]},"a":{"a":0,"k":[500,500,0]},"s":{"a":0,"k":[100,100,100]}},"ao":0,"ip":0,"op":153,"st":0,"bm":0,"sr":1},{"ddd":0,"ind":31,"ty":2,"nm":"Tail","hd":true,"refId":"image_12","ks":{"o":{"a":0,"k":100},"r":{"a":0,"k":0},"p":{"a":0,"k":[500,500,0]},"a":{"a":0,"k":[500,500,0]},"s":{"a":0,"k":[100,100,100]}},"ao":0,"ip":0,"op":153,"st":0,"bm":0,"sr":1}]}